{"objectIdFieldName":"OBJECTID","uniqueIdField":{"name":"OBJECTID","isSystemMaintained":true},"globalIdFieldName":"","geometryProperties":{"shapeAreaFieldName":"Shape__Area","shapeLengthFieldName":"Shape__Length","units":"esriDecimalDegrees"},"geometryType":"esriGeometryPolygon","spatialReference":{"wkid":4269,"latestWkid":4269},"fields":[{"name":"OBJECTID","type":"esriFieldTypeOID","alias":"OBJECTID","sqlType":"sqlTypeOther","domain":null,"defaultValue":null},{"name":"NAME","type":"esriFieldTypeString","alias":"NAME","sqlType":"sqlTypeOther","length":100,"domain":null,"defaultValue":null},{"name":"Shape__Area","type":"esriFieldTypeDouble","alias":"Shape__Area","sqlType":"sqlTypeDouble","domain":null,"defaultValue":null},{"name":"Shape__Length","type":"esriFieldTypeDouble","alias":"Shape__Length","sqlType":"sqlTypeDouble","domain":null,"defaultValue":null},{"name":"County","type":"esriFieldTypeString","alias":"County","sqlType":"sqlTypeOther","length":50,"domain":null,"defaultValue":null},{"name":"POS_Tests","type":"esriFieldTypeInteger","alias":"Positive Tests","sqlType":"sqlTypeOther","domain":null,"defaultValue":null},{"name":"NEG_Tests","type":"esriFieldTypeInteger","alias":"Negative Tests","sqlType":"sqlTypeOther","domain":null,"defaultValue":null},{"name":"TOTAL_Tests","type":"esriFieldTypeInteger","alias":"Total Tests","sqlType":"sqlTypeOther","domain":null,"defaultValue":null},{"name":"NEW_Tests","type":"esriFieldTypeInteger","alias":"New Tests","sqlType":"sqlTypeOther","domain":null,"defaultValue":null},{"name":"TOTAL_Cases","type":"esriFieldTypeInteger","alias":"Total Cases","sqlType":"sqlTypeOther","domain":null,"defaultValue":null},{"name":"NEW_Cases","type":"esriFieldTypeInteger","alias":"New Cases","sqlType":"sqlTypeOther","domain":null,"defaultValue":null},{"name":"TOTAL_Recovered","type":"esriFieldTypeInteger","alias":"Total Recovered","sqlType":"sqlTypeOther","domain":null,"defaultValue":null},{"name":"NEW_Recovered","type":"esriFieldTypeInteger","alias":"New Recovered","sqlType":"sqlTypeOther","domain":null,"defaultValue":null},{"name":"TOTAL_Deaths","type":"esriFieldTypeInteger","alias":"Total Deaths","sqlType":"sqlTypeOther","domain":null,"defaultValue":null},{"name":"NEW_Deaths","type":"esriFieldTypeInteger","alias":"New Deaths","sqlType":"sqlTypeOther","domain":null,"defaultValue":null},{"name":"TOTAL_Active","type":"esriFieldTypeInteger","alias":"Total Active Cases","sqlType":"sqlTypeOther","domain":null,"defaultValue":null},{"name":"NEW_Active","type":"esriFieldTypeInteger","alias":"New Active Cases","sqlType":"sqlTypeOther","domain":null,"defaultValue":null},{"name":"TOTAL_Confirmed","type":"esriFieldTypeInteger","alias":"Total Confirmed","sqlType":"sqlTypeOther","domain":null,"defaultValue":null},{"name":"NEW_Confirmed","type":"esriFieldTypeInteger","alias":"New Confirmed","sqlType":"sqlTypeOther","domain":null,"defaultValue":null},{"name":"NEW_Hospitalized","type":"esriFieldTypeInteger","alias":"New Hospitalized","sqlType":"sqlTypeOther","domain":null,"defaultValue":null},{"name":"TOTAL_Hospitalized","type":"esriFieldTypeInteger","alias":"Total Hospitalized","sqlType":"sqlTypeOther","domain":null,"defaultValue":null},{"name":"TOTAL_Probable","type":"esriFieldTypeInteger","alias":"Total Probable","sqlType":"sqlTypeOther","domain":null,"defaultValue":null},{"name":"NEW_Probable","type":"esriFieldTypeInteger","alias":"New Probable","sqlType":"sqlTypeOther","domain":null,"defaultValue":null}],"features":[{"attributes":{"OBJECTID":83,"NAME":"Anderson","Shape__Area":0.089394019088104,"Shape__Length":1.85454295884033,"County":"Anderson","POS_Tests":437,"NEG_Tests":11118,"TOTAL_Tests":11555,"NEW_Tests":444,"TOTAL_Cases":374,"NEW_Cases":39,"TOTAL_Recovered":200,"NEW_Recovered":21,"TOTAL_Deaths":3,"NEW_Deaths":0,"TOTAL_Active":171,"NEW_Active":18,"TOTAL_Confirmed":363,"NEW_Confirmed":39,"NEW_Hospitalized":0,"TOTAL_Hospitalized":22,"TOTAL_Probable":11,"NEW_Probable":0}},{"attributes":{"OBJECTID":12,"NAME":"Bedford","Shape__Area":0.122179641094817,"Shape__Length":1.85355822897844,"County":"Bedford","POS_Tests":852,"NEG_Tests":5322,"TOTAL_Tests":6174,"NEW_Tests":149,"TOTAL_Cases":711,"NEW_Cases":15,"TOTAL_Recovered":553,"NEW_Recovered":9,"TOTAL_Deaths":10,"NEW_Deaths":0,"TOTAL_Active":148,"NEW_Active":6,"TOTAL_Confirmed":710,"NEW_Confirmed":15,"NEW_Hospitalized":0,"TOTAL_Hospitalized":26,"TOTAL_Probable":1,"NEW_Probable":0}},{"attributes":{"OBJECTID":79,"NAME":"Benton","Shape__Area":0.113031386878674,"Shape__Length":1.96118169089103,"County":"Benton","POS_Tests":38,"NEG_Tests":1411,"TOTAL_Tests":1449,"NEW_Tests":78,"TOTAL_Cases":37,"NEW_Cases":4,"TOTAL_Recovered":14,"NEW_Recovered":1,"TOTAL_Deaths":1,"NEW_Deaths":0,"TOTAL_Active":22,"NEW_Active":3,"TOTAL_Confirmed":31,"NEW_Confirmed":4,"NEW_Hospitalized":0,"TOTAL_Hospitalized":3,"TOTAL_Probable":6,"NEW_Probable":0}},{"attributes":{"OBJECTID":70,"NAME":"Bledsoe","Shape__Area":0.104776326301362,"Shape__Length":1.75119382902414,"County":"Bledsoe","POS_Tests":663,"NEG_Tests":4183,"TOTAL_Tests":4846,"NEW_Tests":17,"TOTAL_Cases":646,"NEW_Cases":3,"TOTAL_Recovered":626,"NEW_Recovered":0,"TOTAL_Deaths":1,"NEW_Deaths":0,"TOTAL_Active":19,"NEW_Active":3,"TOTAL_Confirmed":646,"NEW_Confirmed":3,"NEW_Hospitalized":0,"TOTAL_Hospitalized":9,"TOTAL_Probable":0,"NEW_Probable":0}},{"attributes":{"OBJECTID":26,"NAME":"Blount","Shape__Area":0.146128849463821,"Shape__Length":2.24145929493712,"County":"Blount","POS_Tests":831,"NEG_Tests":11009,"TOTAL_Tests":11840,"NEW_Tests":405,"TOTAL_Cases":709,"NEW_Cases":46,"TOTAL_Recovered":346,"NEW_Recovered":24,"TOTAL_Deaths":7,"NEW_Deaths":1,"TOTAL_Active":356,"NEW_Active":21,"TOTAL_Confirmed":685,"NEW_Confirmed":44,"NEW_Hospitalized":2,"TOTAL_Hospitalized":33,"TOTAL_Probable":24,"NEW_Probable":2}},{"attributes":{"OBJECTID":65,"NAME":"Bradley","Shape__Area":0.0849210460432914,"Shape__Length":1.38676121944032,"County":"Bradley","POS_Tests":1574,"NEG_Tests":10506,"TOTAL_Tests":12080,"NEW_Tests":299,"TOTAL_Cases":1330,"NEW_Cases":46,"TOTAL_Recovered":886,"NEW_Recovered":55,"TOTAL_Deaths":9,"NEW_Deaths":1,"TOTAL_Active":435,"NEW_Active":-10,"TOTAL_Confirmed":1311,"NEW_Confirmed":46,"NEW_Hospitalized":1,"TOTAL_Hospitalized":73,"TOTAL_Probable":19,"NEW_Probable":0}},{"attributes":{"OBJECTID":5,"NAME":"Campbell","Shape__Area":0.129608311519405,"Shape__Length":2.05402948309425,"County":"Campbell","POS_Tests":130,"NEG_Tests":4301,"TOTAL_Tests":4431,"NEW_Tests":111,"TOTAL_Cases":115,"NEW_Cases":9,"TOTAL_Recovered":64,"NEW_Recovered":4,"TOTAL_Deaths":1,"NEW_Deaths":0,"TOTAL_Active":50,"NEW_Active":5,"TOTAL_Confirmed":108,"NEW_Confirmed":9,"NEW_Hospitalized":0,"TOTAL_Hospitalized":7,"TOTAL_Probable":7,"NEW_Probable":0}},{"attributes":{"OBJECTID":84,"NAME":"Cannon","Shape__Area":0.0686209822902129,"Shape__Length":1.29564736936001,"County":"Cannon","POS_Tests":122,"NEG_Tests":1632,"TOTAL_Tests":1754,"NEW_Tests":78,"TOTAL_Cases":87,"NEW_Cases":9,"TOTAL_Recovered":45,"NEW_Recovered":3,"TOTAL_Deaths":0,"NEW_Deaths":0,"TOTAL_Active":42,"NEW_Active":6,"TOTAL_Confirmed":86,"NEW_Confirmed":9,"NEW_Hospitalized":0,"TOTAL_Hospitalized":4,"TOTAL_Probable":1,"NEW_Probable":0}},{"attributes":{"OBJECTID":36,"NAME":"Carroll","Shape__Area":0.155302320728424,"Shape__Length":1.8217653235785,"County":"Carroll","POS_Tests":107,"NEG_Tests":2697,"TOTAL_Tests":2804,"NEW_Tests":151,"TOTAL_Cases":107,"NEW_Cases":17,"TOTAL_Recovered":41,"NEW_Recovered":1,"TOTAL_Deaths":2,"NEW_Deaths":0,"TOTAL_Active":64,"NEW_Active":16,"TOTAL_Confirmed":89,"NEW_Confirmed":14,"NEW_Hospitalized":0,"TOTAL_Hospitalized":10,"TOTAL_Probable":18,"NEW_Probable":3}},{"attributes":{"OBJECTID":31,"NAME":"Carter","Shape__Area":0.0903425571041225,"Shape__Length":1.66555462245196,"County":"Carter","POS_Tests":274,"NEG_Tests":5164,"TOTAL_Tests":5438,"NEW_Tests":423,"TOTAL_Cases":250,"NEW_Cases":25,"TOTAL_Recovered":64,"NEW_Recovered":2,"TOTAL_Deaths":2,"NEW_Deaths":0,"TOTAL_Active":184,"NEW_Active":23,"TOTAL_Confirmed":241,"NEW_Confirmed":24,"NEW_Hospitalized":0,"TOTAL_Hospitalized":24,"TOTAL_Probable":9,"NEW_Probable":1}},{"attributes":{"OBJECTID":86,"NAME":"Cheatham","Shape__Area":0.0797489935714566,"Shape__Length":1.7514065846846,"County":"Cheatham","POS_Tests":470,"NEG_Tests":5017,"TOTAL_Tests":5487,"NEW_Tests":187,"TOTAL_Cases":397,"NEW_Cases":15,"TOTAL_Recovered":171,"NEW_Recovered":12,"TOTAL_Deaths":4,"NEW_Deaths":0,"TOTAL_Active":222,"NEW_Active":3,"TOTAL_Confirmed":396,"NEW_Confirmed":15,"NEW_Hospitalized":0,"TOTAL_Hospitalized":16,"TOTAL_Probable":1,"NEW_Probable":0}},{"attributes":{"OBJECTID":27,"NAME":"Chester","Shape__Area":0.0735041320529035,"Shape__Length":1.56573412313699,"County":"Chester","POS_Tests":141,"NEG_Tests":1347,"TOTAL_Tests":1488,"NEW_Tests":67,"TOTAL_Cases":132,"NEW_Cases":6,"TOTAL_Recovered":43,"NEW_Recovered":0,"TOTAL_Deaths":0,"NEW_Deaths":0,"TOTAL_Active":89,"NEW_Active":6,"TOTAL_Confirmed":127,"NEW_Confirmed":6,"NEW_Hospitalized":1,"TOTAL_Hospitalized":6,"TOTAL_Probable":5,"NEW_Probable":0}},{"attributes":{"OBJECTID":58,"NAME":"Claiborne","Shape__Area":0.115016447381322,"Shape__Length":1.94156374245673,"County":"Claiborne","POS_Tests":153,"NEG_Tests":3499,"TOTAL_Tests":3652,"NEW_Tests":127,"TOTAL_Cases":135,"NEW_Cases":8,"TOTAL_Recovered":54,"NEW_Recovered":-1,"TOTAL_Deaths":0,"NEW_Deaths":0,"TOTAL_Active":81,"NEW_Active":9,"TOTAL_Confirmed":130,"NEW_Confirmed":7,"NEW_Hospitalized":0,"TOTAL_Hospitalized":4,"TOTAL_Probable":5,"NEW_Probable":1}},{"attributes":{"OBJECTID":13,"NAME":"Clay","Shape__Area":0.0676071012571811,"Shape__Length":1.58334370734817,"County":"Clay","POS_Tests":45,"NEG_Tests":1088,"TOTAL_Tests":1133,"NEW_Tests":21,"TOTAL_Cases":41,"NEW_Cases":2,"TOTAL_Recovered":27,"NEW_Recovered":6,"TOTAL_Deaths":0,"NEW_Deaths":0,"TOTAL_Active":14,"NEW_Active":-4,"TOTAL_Confirmed":41,"NEW_Confirmed":2,"NEW_Hospitalized":1,"TOTAL_Hospitalized":2,"TOTAL_Probable":0,"NEW_Probable":0}},{"attributes":{"OBJECTID":55,"NAME":"Cocke","Shape__Area":0.114594253507221,"Shape__Length":1.91991480836266,"County":"Cocke","POS_Tests":269,"NEG_Tests":3399,"TOTAL_Tests":3668,"NEW_Tests":155,"TOTAL_Cases":251,"NEW_Cases":13,"TOTAL_Recovered":132,"NEW_Recovered":5,"TOTAL_Deaths":1,"NEW_Deaths":0,"TOTAL_Active":118,"NEW_Active":8,"TOTAL_Confirmed":238,"NEW_Confirmed":13,"NEW_Hospitalized":0,"TOTAL_Hospitalized":8,"TOTAL_Probable":13,"NEW_Probable":0}},{"attributes":{"OBJECTID":50,"NAME":"Coffee","Shape__Area":0.111793876268848,"Shape__Length":2.00807246732362,"County":"Coffee","POS_Tests":290,"NEG_Tests":6586,"TOTAL_Tests":6876,"NEW_Tests":155,"TOTAL_Cases":233,"NEW_Cases":12,"TOTAL_Recovered":135,"NEW_Recovered":3,"TOTAL_Deaths":0,"NEW_Deaths":0,"TOTAL_Active":98,"NEW_Active":9,"TOTAL_Confirmed":227,"NEW_Confirmed":11,"NEW_Hospitalized":0,"TOTAL_Hospitalized":9,"TOTAL_Probable":6,"NEW_Probable":1}},{"attributes":{"OBJECTID":85,"NAME":"Crockett","Shape__Area":0.0686362688554709,"Shape__Length":1.59127399780242,"County":"Crockett","POS_Tests":143,"NEG_Tests":1308,"TOTAL_Tests":1451,"NEW_Tests":53,"TOTAL_Cases":130,"NEW_Cases":15,"TOTAL_Recovered":48,"NEW_Recovered":5,"TOTAL_Deaths":3,"NEW_Deaths":0,"TOTAL_Active":79,"NEW_Active":10,"TOTAL_Confirmed":117,"NEW_Confirmed":15,"NEW_Hospitalized":1,"TOTAL_Hospitalized":6,"TOTAL_Probable":13,"NEW_Probable":0}},{"attributes":{"OBJECTID":53,"NAME":"Cumberland","Shape__Area":0.177178909998929,"Shape__Length":2.05791747288235,"County":"Cumberland","POS_Tests":374,"NEG_Tests":9893,"TOTAL_Tests":10267,"NEW_Tests":218,"TOTAL_Cases":287,"NEW_Cases":11,"TOTAL_Recovered":191,"NEW_Recovered":9,"TOTAL_Deaths":6,"NEW_Deaths":0,"TOTAL_Active":90,"NEW_Active":2,"TOTAL_Confirmed":286,"NEW_Confirmed":11,"NEW_Hospitalized":1,"TOTAL_Hospitalized":22,"TOTAL_Probable":1,"NEW_Probable":0}},{"attributes":{"OBJECTID":69,"NAME":"Davidson","Shape__Area":0.136388835221396,"Shape__Length":2.07664866585867,"County":"Davidson","POS_Tests":20587,"NEG_Tests":146020,"TOTAL_Tests":166607,"NEW_Tests":3093,"TOTAL_Cases":16956,"NEW_Cases":261,"TOTAL_Recovered":11419,"NEW_Recovered":333,"TOTAL_Deaths":179,"NEW_Deaths":6,"TOTAL_Active":5358,"NEW_Active":-78,"TOTAL_Confirmed":16930,"NEW_Confirmed":258,"NEW_Hospitalized":11,"TOTAL_Hospitalized":607,"TOTAL_Probable":26,"NEW_Probable":3}},{"attributes":{"OBJECTID":91,"NAME":"Decatur","Shape__Area":0.0888473402926593,"Shape__Length":1.66868440999526,"County":"Decatur","POS_Tests":89,"NEG_Tests":1622,"TOTAL_Tests":1711,"NEW_Tests":142,"TOTAL_Cases":85,"NEW_Cases":10,"TOTAL_Recovered":24,"NEW_Recovered":1,"TOTAL_Deaths":0,"NEW_Deaths":0,"TOTAL_Active":61,"NEW_Active":9,"TOTAL_Confirmed":57,"NEW_Confirmed":8,"NEW_Hospitalized":0,"TOTAL_Hospitalized":3,"TOTAL_Probable":28,"NEW_Probable":2}},{"attributes":{"OBJECTID":16,"NAME":"DeKalb","Shape__Area":0.0851476780856046,"Shape__Length":1.75135208710445,"County":"DeKalb","POS_Tests":216,"NEG_Tests":3257,"TOTAL_Tests":3473,"NEW_Tests":51,"TOTAL_Cases":192,"NEW_Cases":8,"TOTAL_Recovered":75,"NEW_Recovered":1,"TOTAL_Deaths":1,"NEW_Deaths":0,"TOTAL_Active":116,"NEW_Active":7,"TOTAL_Confirmed":192,"NEW_Confirmed":8,"NEW_Hospitalized":0,"TOTAL_Hospitalized":7,"TOTAL_Probable":0,"NEW_Probable":0}},{"attributes":{"OBJECTID":47,"NAME":"Dickson","Shape__Area":0.127431690033518,"Shape__Length":1.75072827560832,"County":"Dickson","POS_Tests":540,"NEG_Tests":5920,"TOTAL_Tests":6460,"NEW_Tests":205,"TOTAL_Cases":421,"NEW_Cases":19,"TOTAL_Recovered":151,"NEW_Recovered":6,"TOTAL_Deaths":0,"NEW_Deaths":0,"TOTAL_Active":270,"NEW_Active":13,"TOTAL_Confirmed":421,"NEW_Confirmed":19,"NEW_Hospitalized":1,"TOTAL_Hospitalized":25,"TOTAL_Probable":0,"NEW_Probable":0}},{"attributes":{"OBJECTID":88,"NAME":"Dyer","Shape__Area":0.136411128649797,"Shape__Length":1.92396788966357,"County":"Dyer","POS_Tests":440,"NEG_Tests":4293,"TOTAL_Tests":4733,"NEW_Tests":129,"TOTAL_Cases":400,"NEW_Cases":17,"TOTAL_Recovered":179,"NEW_Recovered":10,"TOTAL_Deaths":5,"NEW_Deaths":0,"TOTAL_Active":216,"NEW_Active":7,"TOTAL_Confirmed":384,"NEW_Confirmed":17,"NEW_Hospitalized":2,"TOTAL_Hospitalized":31,"TOTAL_Probable":16,"NEW_Probable":0}},{"attributes":{"OBJECTID":93,"NAME":"Fayette","Shape__Area":0.18104077591579,"Shape__Length":1.735740757233,"County":"Fayette","POS_Tests":624,"NEG_Tests":8065,"TOTAL_Tests":8689,"NEW_Tests":227,"TOTAL_Cases":510,"NEW_Cases":15,"TOTAL_Recovered":298,"NEW_Recovered":9,"TOTAL_Deaths":8,"NEW_Deaths":0,"TOTAL_Active":204,"NEW_Active":6,"TOTAL_Confirmed":505,"NEW_Confirmed":15,"NEW_Hospitalized":0,"TOTAL_Hospitalized":42,"TOTAL_Probable":5,"NEW_Probable":0}},{"attributes":{"OBJECTID":78,"NAME":"Fentress","Shape__Area":0.129783193706999,"Shape__Length":1.897406012842,"County":"Fentress","POS_Tests":52,"NEG_Tests":1678,"TOTAL_Tests":1730,"NEW_Tests":43,"TOTAL_Cases":48,"NEW_Cases":2,"TOTAL_Recovered":25,"NEW_Recovered":1,"TOTAL_Deaths":0,"NEW_Deaths":0,"TOTAL_Active":23,"NEW_Active":1,"TOTAL_Confirmed":48,"NEW_Confirmed":2,"NEW_Hospitalized":1,"TOTAL_Hospitalized":3,"TOTAL_Probable":0,"NEW_Probable":0}},{"attributes":{"OBJECTID":81,"NAME":"Franklin","Shape__Area":0.147515722583876,"Shape__Length":1.90448079671003,"County":"Franklin","POS_Tests":222,"NEG_Tests":4802,"TOTAL_Tests":5024,"NEW_Tests":234,"TOTAL_Cases":171,"NEW_Cases":3,"TOTAL_Recovered":99,"NEW_Recovered":5,"TOTAL_Deaths":3,"NEW_Deaths":0,"TOTAL_Active":69,"NEW_Active":-2,"TOTAL_Confirmed":169,"NEW_Confirmed":3,"NEW_Hospitalized":0,"TOTAL_Hospitalized":8,"TOTAL_Probable":2,"NEW_Probable":0}},{"attributes":{"OBJECTID":89,"NAME":"Gibson","Shape__Area":0.156268564158609,"Shape__Length":2.00243835921869,"County":"Gibson","POS_Tests":385,"NEG_Tests":4822,"TOTAL_Tests":5207,"NEW_Tests":182,"TOTAL_Cases":346,"NEW_Cases":16,"TOTAL_Recovered":132,"NEW_Recovered":9,"TOTAL_Deaths":1,"NEW_Deaths":0,"TOTAL_Active":213,"NEW_Active":7,"TOTAL_Confirmed":283,"NEW_Confirmed":15,"NEW_Hospitalized":1,"TOTAL_Hospitalized":15,"TOTAL_Probable":63,"NEW_Probable":1}},{"attributes":{"OBJECTID":41,"NAME":"Giles","Shape__Area":0.156682408820643,"Shape__Length":1.92951124246309,"County":"Giles","POS_Tests":268,"NEG_Tests":3656,"TOTAL_Tests":3924,"NEW_Tests":112,"TOTAL_Cases":234,"NEW_Cases":11,"TOTAL_Recovered":74,"NEW_Recovered":1,"TOTAL_Deaths":4,"NEW_Deaths":0,"TOTAL_Active":156,"NEW_Active":10,"TOTAL_Confirmed":234,"NEW_Confirmed":11,"NEW_Hospitalized":1,"TOTAL_Hospitalized":16,"TOTAL_Probable":0,"NEW_Probable":0}},{"attributes":{"OBJECTID":64,"NAME":"Grainger","Shape__Area":0.078567979438958,"Shape__Length":2.18524904343152,"County":"Grainger","POS_Tests":114,"NEG_Tests":2183,"TOTAL_Tests":2297,"NEW_Tests":65,"TOTAL_Cases":97,"NEW_Cases":5,"TOTAL_Recovered":58,"NEW_Recovered":7,"TOTAL_Deaths":0,"NEW_Deaths":0,"TOTAL_Active":39,"NEW_Active":-2,"TOTAL_Confirmed":92,"NEW_Confirmed":5,"NEW_Hospitalized":0,"TOTAL_Hospitalized":8,"TOTAL_Probable":5,"NEW_Probable":0}},{"attributes":{"OBJECTID":48,"NAME":"Greene","Shape__Area":0.161933489713419,"Shape__Length":2.05274405099762,"County":"Greene","POS_Tests":288,"NEG_Tests":5862,"TOTAL_Tests":6150,"NEW_Tests":240,"TOTAL_Cases":243,"NEW_Cases":6,"TOTAL_Recovered":109,"NEW_Recovered":2,"TOTAL_Deaths":4,"NEW_Deaths":0,"TOTAL_Active":130,"NEW_Active":4,"TOTAL_Confirmed":234,"NEW_Confirmed":6,"NEW_Hospitalized":0,"TOTAL_Hospitalized":16,"TOTAL_Probable":9,"NEW_Probable":0}},{"attributes":{"OBJECTID":11,"NAME":"Grundy","Shape__Area":0.0927867343054913,"Shape__Length":1.46980446774723,"County":"Grundy","POS_Tests":92,"NEG_Tests":1192,"TOTAL_Tests":1284,"NEW_Tests":41,"TOTAL_Cases":77,"NEW_Cases":3,"TOTAL_Recovered":59,"NEW_Recovered":1,"TOTAL_Deaths":2,"NEW_Deaths":0,"TOTAL_Active":16,"NEW_Active":2,"TOTAL_Confirmed":75,"NEW_Confirmed":3,"NEW_Hospitalized":1,"TOTAL_Hospitalized":14,"TOTAL_Probable":2,"NEW_Probable":0}},{"attributes":{"OBJECTID":94,"NAME":"Hamblen","Shape__Area":0.0456363316495754,"Shape__Length":1.49560686777259,"County":"Hamblen","POS_Tests":876,"NEG_Tests":8530,"TOTAL_Tests":9406,"NEW_Tests":368,"TOTAL_Cases":793,"NEW_Cases":50,"TOTAL_Recovered":501,"NEW_Recovered":23,"TOTAL_Deaths":6,"NEW_Deaths":0,"TOTAL_Active":286,"NEW_Active":27,"TOTAL_Confirmed":782,"NEW_Confirmed":50,"NEW_Hospitalized":3,"TOTAL_Hospitalized":49,"TOTAL_Probable":11,"NEW_Probable":0}},{"attributes":{"OBJECTID":1,"NAME":"Hamilton","Shape__Area":0.147595160449555,"Shape__Length":1.98811891308672,"County":"Hamilton","POS_Tests":5183,"NEG_Tests":45601,"TOTAL_Tests":50784,"NEW_Tests":1464,"TOTAL_Cases":4604,"NEW_Cases":81,"TOTAL_Recovered":2867,"NEW_Recovered":98,"TOTAL_Deaths":41,"NEW_Deaths":1,"TOTAL_Active":1696,"NEW_Active":-18,"TOTAL_Confirmed":4595,"NEW_Confirmed":81,"NEW_Hospitalized":2,"TOTAL_Hospitalized":194,"TOTAL_Probable":9,"NEW_Probable":0}},{"attributes":{"OBJECTID":56,"NAME":"Hancock","Shape__Area":0.0582369734152053,"Shape__Length":1.64062899984068,"County":"Hancock","POS_Tests":46,"NEG_Tests":773,"TOTAL_Tests":819,"NEW_Tests":36,"TOTAL_Cases":43,"NEW_Cases":4,"TOTAL_Recovered":5,"NEW_Recovered":0,"TOTAL_Deaths":0,"NEW_Deaths":0,"TOTAL_Active":38,"NEW_Active":4,"TOTAL_Confirmed":38,"NEW_Confirmed":2,"NEW_Hospitalized":1,"TOTAL_Hospitalized":5,"TOTAL_Probable":5,"NEW_Probable":2}},{"attributes":{"OBJECTID":35,"NAME":"Hardeman","Shape__Area":0.171869145546225,"Shape__Length":1.64982870558123,"County":"Hardeman","POS_Tests":680,"NEG_Tests":7499,"TOTAL_Tests":8179,"NEW_Tests":213,"TOTAL_Cases":614,"NEW_Cases":35,"TOTAL_Recovered":356,"NEW_Recovered":11,"TOTAL_Deaths":9,"NEW_Deaths":1,"TOTAL_Active":249,"NEW_Active":23,"TOTAL_Confirmed":590,"NEW_Confirmed":36,"NEW_Hospitalized":3,"TOTAL_Hospitalized":31,"TOTAL_Probable":24,"NEW_Probable":-1}},{"attributes":{"OBJECTID":57,"NAME":"Hardin","Shape__Area":0.152859518943615,"Shape__Length":1.74874088886125,"County":"Hardin","POS_Tests":296,"NEG_Tests":4917,"TOTAL_Tests":5213,"NEW_Tests":331,"TOTAL_Cases":260,"NEW_Cases":22,"TOTAL_Recovered":95,"NEW_Recovered":10,"TOTAL_Deaths":7,"NEW_Deaths":0,"TOTAL_Active":158,"NEW_Active":12,"TOTAL_Confirmed":253,"NEW_Confirmed":21,"NEW_Hospitalized":1,"TOTAL_Hospitalized":12,"TOTAL_Probable":7,"NEW_Probable":1}},{"attributes":{"OBJECTID":24,"NAME":"Hawkins","Shape__Area":0.130061928909754,"Shape__Length":2.19941680343838,"County":"Hawkins","POS_Tests":197,"NEG_Tests":4002,"TOTAL_Tests":4199,"NEW_Tests":173,"TOTAL_Cases":162,"NEW_Cases":7,"TOTAL_Recovered":61,"NEW_Recovered":2,"TOTAL_Deaths":2,"NEW_Deaths":0,"TOTAL_Active":99,"NEW_Active":5,"TOTAL_Confirmed":158,"NEW_Confirmed":7,"NEW_Hospitalized":2,"TOTAL_Hospitalized":16,"TOTAL_Probable":4,"NEW_Probable":0}},{"attributes":{"OBJECTID":22,"NAME":"Haywood","Shape__Area":0.13754930837672,"Shape__Length":1.72540566033752,"County":"Haywood","POS_Tests":244,"NEG_Tests":2291,"TOTAL_Tests":2535,"NEW_Tests":79,"TOTAL_Cases":224,"NEW_Cases":18,"TOTAL_Recovered":95,"NEW_Recovered":10,"TOTAL_Deaths":4,"NEW_Deaths":0,"TOTAL_Active":125,"NEW_Active":8,"TOTAL_Confirmed":215,"NEW_Confirmed":18,"NEW_Hospitalized":0,"TOTAL_Hospitalized":14,"TOTAL_Probable":9,"NEW_Probable":0}},{"attributes":{"OBJECTID":76,"NAME":"Henderson","Shape__Area":0.135561542823325,"Shape__Length":1.65685204405693,"County":"Henderson","POS_Tests":267,"NEG_Tests":2748,"TOTAL_Tests":3015,"NEW_Tests":232,"TOTAL_Cases":252,"NEW_Cases":41,"TOTAL_Recovered":70,"NEW_Recovered":7,"TOTAL_Deaths":0,"NEW_Deaths":0,"TOTAL_Active":182,"NEW_Active":34,"TOTAL_Confirmed":192,"NEW_Confirmed":37,"NEW_Hospitalized":0,"TOTAL_Hospitalized":8,"TOTAL_Probable":60,"NEW_Probable":4}},{"attributes":{"OBJECTID":46,"NAME":"Henry","Shape__Area":0.154262111414027,"Shape__Length":1.98178139454221,"County":"Henry","POS_Tests":105,"NEG_Tests":3883,"TOTAL_Tests":3988,"NEW_Tests":154,"TOTAL_Cases":88,"NEW_Cases":13,"TOTAL_Recovered":51,"NEW_Recovered":2,"TOTAL_Deaths":1,"NEW_Deaths":0,"TOTAL_Active":36,"NEW_Active":11,"TOTAL_Confirmed":85,"NEW_Confirmed":13,"NEW_Hospitalized":0,"TOTAL_Hospitalized":9,"TOTAL_Probable":3,"NEW_Probable":0}},{"attributes":{"OBJECTID":17,"NAME":"Hickman","Shape__Area":0.158212285997251,"Shape__Length":1.86503268442306,"County":"Hickman","POS_Tests":202,"NEG_Tests":2425,"TOTAL_Tests":2627,"NEW_Tests":72,"TOTAL_Cases":161,"NEW_Cases":7,"TOTAL_Recovered":100,"NEW_Recovered":16,"TOTAL_Deaths":0,"NEW_Deaths":0,"TOTAL_Active":61,"NEW_Active":-9,"TOTAL_Confirmed":161,"NEW_Confirmed":7,"NEW_Hospitalized":1,"TOTAL_Hospitalized":4,"TOTAL_Probable":0,"NEW_Probable":0}},{"attributes":{"OBJECTID":40,"NAME":"Houston","Shape__Area":0.053774471509314,"Shape__Length":1.22269170743502,"County":"Houston","POS_Tests":39,"NEG_Tests":947,"TOTAL_Tests":986,"NEW_Tests":12,"TOTAL_Cases":34,"NEW_Cases":3,"TOTAL_Recovered":13,"NEW_Recovered":2,"TOTAL_Deaths":0,"NEW_Deaths":0,"TOTAL_Active":21,"NEW_Active":1,"TOTAL_Confirmed":34,"NEW_Confirmed":3,"NEW_Hospitalized":0,"TOTAL_Hospitalized":4,"TOTAL_Probable":0,"NEW_Probable":0}},{"attributes":{"OBJECTID":42,"NAME":"Humphreys","Shape__Area":0.144194442048502,"Shape__Length":1.81897707484499,"County":"Humphreys","POS_Tests":76,"NEG_Tests":2053,"TOTAL_Tests":2129,"NEW_Tests":54,"TOTAL_Cases":63,"NEW_Cases":0,"TOTAL_Recovered":21,"NEW_Recovered":2,"TOTAL_Deaths":3,"NEW_Deaths":1,"TOTAL_Active":39,"NEW_Active":-3,"TOTAL_Confirmed":62,"NEW_Confirmed":0,"NEW_Hospitalized":1,"TOTAL_Hospitalized":3,"TOTAL_Probable":1,"NEW_Probable":0}},{"attributes":{"OBJECTID":28,"NAME":"Jackson","Shape__Area":0.0830930928307225,"Shape__Length":1.42697708222725,"County":"Jackson","POS_Tests":102,"NEG_Tests":1288,"TOTAL_Tests":1390,"NEW_Tests":42,"TOTAL_Cases":91,"NEW_Cases":1,"TOTAL_Recovered":39,"NEW_Recovered":3,"TOTAL_Deaths":0,"NEW_Deaths":0,"TOTAL_Active":52,"NEW_Active":-2,"TOTAL_Confirmed":91,"NEW_Confirmed":1,"NEW_Hospitalized":0,"TOTAL_Hospitalized":3,"TOTAL_Probable":0,"NEW_Probable":0}},{"attributes":{"OBJECTID":21,"NAME":"Jefferson","Shape__Area":0.0814204375351437,"Shape__Length":1.7773574586873,"County":"Jefferson","POS_Tests":347,"NEG_Tests":6173,"TOTAL_Tests":6520,"NEW_Tests":415,"TOTAL_Cases":317,"NEW_Cases":28,"TOTAL_Recovered":182,"NEW_Recovered":11,"TOTAL_Deaths":1,"NEW_Deaths":0,"TOTAL_Active":134,"NEW_Active":17,"TOTAL_Confirmed":306,"NEW_Confirmed":28,"NEW_Hospitalized":1,"TOTAL_Hospitalized":17,"TOTAL_Probable":11,"NEW_Probable":0}},{"attributes":{"OBJECTID":73,"NAME":"Johnson","Shape__Area":0.0788110607547878,"Shape__Length":1.59378928064322,"County":"Johnson","POS_Tests":59,"NEG_Tests":2911,"TOTAL_Tests":2970,"NEW_Tests":85,"TOTAL_Cases":54,"NEW_Cases":2,"TOTAL_Recovered":38,"NEW_Recovered":0,"TOTAL_Deaths":0,"NEW_Deaths":0,"TOTAL_Active":16,"NEW_Active":2,"TOTAL_Confirmed":52,"NEW_Confirmed":2,"NEW_Hospitalized":0,"TOTAL_Hospitalized":5,"TOTAL_Probable":2,"NEW_Probable":0}},{"attributes":{"OBJECTID":54,"NAME":"Knox","Shape__Area":0.136128933981126,"Shape__Length":2.30495371045623,"County":"Knox","POS_Tests":3066,"NEG_Tests":56400,"TOTAL_Tests":59466,"NEW_Tests":1768,"TOTAL_Cases":2703,"NEW_Cases":125,"TOTAL_Recovered":1246,"NEW_Recovered":90,"TOTAL_Deaths":21,"NEW_Deaths":0,"TOTAL_Active":1436,"NEW_Active":35,"TOTAL_Confirmed":2616,"NEW_Confirmed":117,"NEW_Hospitalized":5,"TOTAL_Hospitalized":137,"TOTAL_Probable":87,"NEW_Probable":8}},{"attributes":{"OBJECTID":20,"NAME":"Lake","Shape__Area":0.0504072039923358,"Shape__Length":1.48799406630476,"County":"Lake","POS_Tests":871,"NEG_Tests":4058,"TOTAL_Tests":4929,"NEW_Tests":12,"TOTAL_Cases":703,"NEW_Cases":1,"TOTAL_Recovered":691,"NEW_Recovered":0,"TOTAL_Deaths":0,"NEW_Deaths":0,"TOTAL_Active":12,"NEW_Active":1,"TOTAL_Confirmed":699,"NEW_Confirmed":1,"NEW_Hospitalized":0,"TOTAL_Hospitalized":3,"TOTAL_Probable":4,"NEW_Probable":0}},{"attributes":{"OBJECTID":14,"NAME":"Lauderdale","Shape__Area":0.13101453012996,"Shape__Length":2.86158056604156,"County":"Lauderdale","POS_Tests":322,"NEG_Tests":5381,"TOTAL_Tests":5703,"NEW_Tests":102,"TOTAL_Cases":287,"NEW_Cases":19,"TOTAL_Recovered":139,"NEW_Recovered":16,"TOTAL_Deaths":6,"NEW_Deaths":1,"TOTAL_Active":142,"NEW_Active":2,"TOTAL_Confirmed":282,"NEW_Confirmed":19,"NEW_Hospitalized":1,"TOTAL_Hospitalized":22,"TOTAL_Probable":5,"NEW_Probable":0}},{"attributes":{"OBJECTID":23,"NAME":"Lawrence","Shape__Area":0.158457170839711,"Shape__Length":1.89892349156785,"County":"Lawrence","POS_Tests":407,"NEG_Tests":4662,"TOTAL_Tests":5069,"NEW_Tests":86,"TOTAL_Cases":332,"NEW_Cases":8,"TOTAL_Recovered":164,"NEW_Recovered":7,"TOTAL_Deaths":6,"NEW_Deaths":0,"TOTAL_Active":162,"NEW_Active":1,"TOTAL_Confirmed":332,"NEW_Confirmed":8,"NEW_Hospitalized":0,"TOTAL_Hospitalized":19,"TOTAL_Probable":0,"NEW_Probable":0}},{"attributes":{"OBJECTID":95,"NAME":"Lewis","Shape__Area":0.0727056417476888,"Shape__Length":1.54080979418891,"County":"Lewis","POS_Tests":30,"NEG_Tests":1437,"TOTAL_Tests":1467,"NEW_Tests":21,"TOTAL_Cases":27,"NEW_Cases":5,"TOTAL_Recovered":11,"NEW_Recovered":2,"TOTAL_Deaths":0,"NEW_Deaths":0,"TOTAL_Active":16,"NEW_Active":3,"TOTAL_Confirmed":27,"NEW_Confirmed":5,"NEW_Hospitalized":0,"TOTAL_Hospitalized":2,"TOTAL_Probable":0,"NEW_Probable":0}},{"attributes":{"OBJECTID":68,"NAME":"Lincoln","Shape__Area":0.146200404290994,"Shape__Length":1.87390534972052,"County":"Lincoln","POS_Tests":203,"NEG_Tests":3281,"TOTAL_Tests":3484,"NEW_Tests":32,"TOTAL_Cases":165,"NEW_Cases":13,"TOTAL_Recovered":69,"NEW_Recovered":1,"TOTAL_Deaths":1,"NEW_Deaths":1,"TOTAL_Active":95,"NEW_Active":11,"TOTAL_Confirmed":165,"NEW_Confirmed":13,"NEW_Hospitalized":1,"TOTAL_Hospitalized":6,"TOTAL_Probable":0,"NEW_Probable":0}},{"attributes":{"OBJECTID":15,"NAME":"Loudon","Shape__Area":0.0638296899730904,"Shape__Length":1.91687580612665,"County":"Loudon","POS_Tests":513,"NEG_Tests":5475,"TOTAL_Tests":5988,"NEW_Tests":254,"TOTAL_Cases":484,"NEW_Cases":41,"TOTAL_Recovered":298,"NEW_Recovered":9,"TOTAL_Deaths":3,"NEW_Deaths":0,"TOTAL_Active":183,"NEW_Active":32,"TOTAL_Confirmed":466,"NEW_Confirmed":41,"NEW_Hospitalized":0,"TOTAL_Hospitalized":13,"TOTAL_Probable":18,"NEW_Probable":0}},{"attributes":{"OBJECTID":34,"NAME":"Macon","Shape__Area":0.080073149757709,"Shape__Length":1.25104872582786,"County":"Macon","POS_Tests":862,"NEG_Tests":4005,"TOTAL_Tests":4867,"NEW_Tests":119,"TOTAL_Cases":747,"NEW_Cases":11,"TOTAL_Recovered":554,"NEW_Recovered":18,"TOTAL_Deaths":10,"NEW_Deaths":1,"TOTAL_Active":183,"NEW_Active":-8,"TOTAL_Confirmed":745,"NEW_Confirmed":11,"NEW_Hospitalized":1,"TOTAL_Hospitalized":45,"TOTAL_Probable":2,"NEW_Probable":0}},{"attributes":{"OBJECTID":87,"NAME":"Madison","Shape__Area":0.143919527333537,"Shape__Length":1.63340475071508,"County":"Madison","POS_Tests":638,"NEG_Tests":10401,"TOTAL_Tests":11039,"NEW_Tests":412,"TOTAL_Cases":562,"NEW_Cases":32,"TOTAL_Recovered":336,"NEW_Recovered":23,"TOTAL_Deaths":8,"NEW_Deaths":5,"TOTAL_Active":218,"NEW_Active":4,"TOTAL_Confirmed":540,"NEW_Confirmed":32,"NEW_Hospitalized":3,"TOTAL_Hospitalized":27,"TOTAL_Probable":22,"NEW_Probable":0}},{"attributes":{"OBJECTID":2,"NAME":"Marion","Shape__Area":0.131206024873109,"Shape__Length":1.6307075086172,"County":"Marion","POS_Tests":175,"NEG_Tests":2603,"TOTAL_Tests":2778,"NEW_Tests":95,"TOTAL_Cases":143,"NEW_Cases":8,"TOTAL_Recovered":81,"NEW_Recovered":5,"TOTAL_Deaths":4,"NEW_Deaths":0,"TOTAL_Active":58,"NEW_Active":3,"TOTAL_Confirmed":142,"NEW_Confirmed":8,"NEW_Hospitalized":0,"TOTAL_Hospitalized":13,"TOTAL_Probable":1,"NEW_Probable":0}},{"attributes":{"OBJECTID":72,"NAME":"Marshall","Shape__Area":0.0967451295259707,"Shape__Length":1.83650138304939,"County":"Marshall","POS_Tests":208,"NEG_Tests":3266,"TOTAL_Tests":3474,"NEW_Tests":103,"TOTAL_Cases":178,"NEW_Cases":5,"TOTAL_Recovered":108,"NEW_Recovered":5,"TOTAL_Deaths":2,"NEW_Deaths":0,"TOTAL_Active":68,"NEW_Active":0,"TOTAL_Confirmed":178,"NEW_Confirmed":5,"NEW_Hospitalized":0,"TOTAL_Hospitalized":12,"TOTAL_Probable":0,"NEW_Probable":0}},{"attributes":{"OBJECTID":92,"NAME":"Maury","Shape__Area":0.158609687789294,"Shape__Length":2.15931734141697,"County":"Maury","POS_Tests":898,"NEG_Tests":8408,"TOTAL_Tests":9306,"NEW_Tests":315,"TOTAL_Cases":758,"NEW_Cases":46,"TOTAL_Recovered":405,"NEW_Recovered":25,"TOTAL_Deaths":4,"NEW_Deaths":0,"TOTAL_Active":349,"NEW_Active":21,"TOTAL_Confirmed":756,"NEW_Confirmed":46,"NEW_Hospitalized":0,"TOTAL_Hospitalized":32,"TOTAL_Probable":2,"NEW_Probable":0}},{"attributes":{"OBJECTID":38,"NAME":"McMinn","Shape__Area":0.111094595991062,"Shape__Length":1.73240292196527,"County":"McMinn","POS_Tests":479,"NEG_Tests":6443,"TOTAL_Tests":6922,"NEW_Tests":134,"TOTAL_Cases":393,"NEW_Cases":9,"TOTAL_Recovered":240,"NEW_Recovered":12,"TOTAL_Deaths":20,"NEW_Deaths":1,"TOTAL_Active":133,"NEW_Active":-4,"TOTAL_Confirmed":388,"NEW_Confirmed":9,"NEW_Hospitalized":1,"TOTAL_Hospitalized":32,"TOTAL_Probable":5,"NEW_Probable":0}},{"attributes":{"OBJECTID":77,"NAME":"McNairy","Shape__Area":0.144441284037384,"Shape__Length":1.68039629511652,"County":"McNairy","POS_Tests":213,"NEG_Tests":2529,"TOTAL_Tests":2742,"NEW_Tests":146,"TOTAL_Cases":195,"NEW_Cases":17,"TOTAL_Recovered":75,"NEW_Recovered":5,"TOTAL_Deaths":1,"NEW_Deaths":0,"TOTAL_Active":119,"NEW_Active":12,"TOTAL_Confirmed":183,"NEW_Confirmed":16,"NEW_Hospitalized":1,"TOTAL_Hospitalized":13,"TOTAL_Probable":12,"NEW_Probable":1}},{"attributes":{"OBJECTID":67,"NAME":"Meigs","Shape__Area":0.0557760140818573,"Shape__Length":1.81287432623383,"County":"Meigs","POS_Tests":76,"NEG_Tests":1333,"TOTAL_Tests":1409,"NEW_Tests":31,"TOTAL_Cases":62,"NEW_Cases":1,"TOTAL_Recovered":32,"NEW_Recovered":1,"TOTAL_Deaths":0,"NEW_Deaths":0,"TOTAL_Active":30,"NEW_Active":0,"TOTAL_Confirmed":62,"NEW_Confirmed":1,"NEW_Hospitalized":0,"TOTAL_Hospitalized":4,"TOTAL_Probable":0,"NEW_Probable":0}},{"attributes":{"OBJECTID":6,"NAME":"Monroe","Shape__Area":0.167785503020696,"Shape__Length":2.60716958644448,"County":"Monroe","POS_Tests":261,"NEG_Tests":3189,"TOTAL_Tests":3450,"NEW_Tests":138,"TOTAL_Cases":225,"NEW_Cases":12,"TOTAL_Recovered":139,"NEW_Recovered":2,"TOTAL_Deaths":7,"NEW_Deaths":0,"TOTAL_Active":79,"NEW_Active":10,"TOTAL_Confirmed":215,"NEW_Confirmed":12,"NEW_Hospitalized":1,"TOTAL_Hospitalized":18,"TOTAL_Probable":10,"NEW_Probable":0}},{"attributes":{"OBJECTID":45,"NAME":"Montgomery","Shape__Area":0.14167050624792,"Shape__Length":1.77853309171332,"County":"Montgomery","POS_Tests":1464,"NEG_Tests":19648,"TOTAL_Tests":21112,"NEW_Tests":741,"TOTAL_Cases":1288,"NEW_Cases":66,"TOTAL_Recovered":461,"NEW_Recovered":25,"TOTAL_Deaths":9,"NEW_Deaths":0,"TOTAL_Active":818,"NEW_Active":41,"TOTAL_Confirmed":1281,"NEW_Confirmed":66,"NEW_Hospitalized":2,"TOTAL_Hospitalized":58,"TOTAL_Probable":7,"NEW_Probable":0}},{"attributes":{"OBJECTID":29,"NAME":"Moore","Shape__Area":0.0334671317259563,"Shape__Length":1.63419910900472,"County":"Moore","POS_Tests":42,"NEG_Tests":749,"TOTAL_Tests":791,"NEW_Tests":19,"TOTAL_Cases":35,"NEW_Cases":1,"TOTAL_Recovered":19,"NEW_Recovered":3,"TOTAL_Deaths":0,"NEW_Deaths":0,"TOTAL_Active":16,"NEW_Active":-2,"TOTAL_Confirmed":35,"NEW_Confirmed":1,"NEW_Hospitalized":0,"TOTAL_Hospitalized":0,"TOTAL_Probable":0,"NEW_Probable":0}},{"attributes":{"OBJECTID":4,"NAME":"Morgan","Shape__Area":0.135494280748617,"Shape__Length":1.90603154444765,"County":"Morgan","POS_Tests":59,"NEG_Tests":4281,"TOTAL_Tests":4340,"NEW_Tests":63,"TOTAL_Cases":50,"NEW_Cases":4,"TOTAL_Recovered":36,"NEW_Recovered":2,"TOTAL_Deaths":1,"NEW_Deaths":0,"TOTAL_Active":13,"NEW_Active":2,"TOTAL_Confirmed":50,"NEW_Confirmed":4,"NEW_Hospitalized":0,"TOTAL_Hospitalized":2,"TOTAL_Probable":0,"NEW_Probable":0}},{"attributes":{"OBJECTID":61,"NAME":"Obion","Shape__Area":0.144443055218289,"Shape__Length":1.93228668849445,"County":"Obion","POS_Tests":259,"NEG_Tests":3563,"TOTAL_Tests":3822,"NEW_Tests":183,"TOTAL_Cases":230,"NEW_Cases":39,"TOTAL_Recovered":103,"NEW_Recovered":10,"TOTAL_Deaths":4,"NEW_Deaths":1,"TOTAL_Active":123,"NEW_Active":28,"TOTAL_Confirmed":224,"NEW_Confirmed":40,"NEW_Hospitalized":0,"TOTAL_Hospitalized":15,"TOTAL_Probable":6,"NEW_Probable":-1}},{"attributes":{"OBJECTID":60,"NAME":"Overton","Shape__Area":0.113059244024043,"Shape__Length":1.58148171365898,"County":"Overton","POS_Tests":115,"NEG_Tests":3080,"TOTAL_Tests":3195,"NEW_Tests":82,"TOTAL_Cases":102,"NEW_Cases":2,"TOTAL_Recovered":75,"NEW_Recovered":2,"TOTAL_Deaths":1,"NEW_Deaths":0,"TOTAL_Active":26,"NEW_Active":0,"TOTAL_Confirmed":100,"NEW_Confirmed":2,"NEW_Hospitalized":0,"TOTAL_Hospitalized":3,"TOTAL_Probable":2,"NEW_Probable":0}},{"attributes":{"OBJECTID":51,"NAME":"Perry","Shape__Area":0.108990224866375,"Shape__Length":1.76515792395873,"County":"Perry","POS_Tests":65,"NEG_Tests":1281,"TOTAL_Tests":1346,"NEW_Tests":105,"TOTAL_Cases":56,"NEW_Cases":3,"TOTAL_Recovered":38,"NEW_Recovered":0,"TOTAL_Deaths":0,"NEW_Deaths":0,"TOTAL_Active":18,"NEW_Active":3,"TOTAL_Confirmed":56,"NEW_Confirmed":3,"NEW_Hospitalized":0,"TOTAL_Hospitalized":3,"TOTAL_Probable":0,"NEW_Probable":0}},{"attributes":{"OBJECTID":80,"NAME":"Pickett","Shape__Area":0.0454920331712856,"Shape__Length":1.53134965864132,"County":"Pickett","POS_Tests":16,"NEG_Tests":552,"TOTAL_Tests":568,"NEW_Tests":11,"TOTAL_Cases":16,"NEW_Cases":3,"TOTAL_Recovered":6,"NEW_Recovered":0,"TOTAL_Deaths":1,"NEW_Deaths":0,"TOTAL_Active":9,"NEW_Active":3,"TOTAL_Confirmed":16,"NEW_Confirmed":3,"NEW_Hospitalized":0,"TOTAL_Hospitalized":0,"TOTAL_Probable":0,"NEW_Probable":0}},{"attributes":{"OBJECTID":75,"NAME":"Polk","Shape__Area":0.113273462854977,"Shape__Length":1.48635780675262,"County":"Polk","POS_Tests":95,"NEG_Tests":1474,"TOTAL_Tests":1569,"NEW_Tests":34,"TOTAL_Cases":85,"NEW_Cases":6,"TOTAL_Recovered":49,"NEW_Recovered":2,"TOTAL_Deaths":0,"NEW_Deaths":0,"TOTAL_Active":36,"NEW_Active":4,"TOTAL_Confirmed":82,"NEW_Confirmed":6,"NEW_Hospitalized":0,"TOTAL_Hospitalized":2,"TOTAL_Probable":3,"NEW_Probable":0}},{"attributes":{"OBJECTID":18,"NAME":"Putnam","Shape__Area":0.104400764515958,"Shape__Length":2.50687671104979,"County":"Putnam","POS_Tests":1551,"NEG_Tests":14342,"TOTAL_Tests":15893,"NEW_Tests":476,"TOTAL_Cases":1313,"NEW_Cases":38,"TOTAL_Recovered":923,"NEW_Recovered":29,"TOTAL_Deaths":9,"NEW_Deaths":1,"TOTAL_Active":381,"NEW_Active":8,"TOTAL_Confirmed":1307,"NEW_Confirmed":37,"NEW_Hospitalized":1,"TOTAL_Hospitalized":37,"TOTAL_Probable":6,"NEW_Probable":1}},{"attributes":{"OBJECTID":59,"NAME":"Rhea","Shape__Area":0.0866693867296817,"Shape__Length":1.75978461271075,"County":"Rhea","POS_Tests":472,"NEG_Tests":4118,"TOTAL_Tests":4590,"NEW_Tests":53,"TOTAL_Cases":410,"NEW_Cases":1,"TOTAL_Recovered":305,"NEW_Recovered":5,"TOTAL_Deaths":1,"NEW_Deaths":0,"TOTAL_Active":104,"NEW_Active":-4,"TOTAL_Confirmed":410,"NEW_Confirmed":1,"NEW_Hospitalized":0,"TOTAL_Hospitalized":10,"TOTAL_Probable":0,"NEW_Probable":0}},{"attributes":{"OBJECTID":44,"NAME":"Roane","Shape__Area":0.102059853046512,"Shape__Length":1.90231210367639,"County":"Roane","POS_Tests":210,"NEG_Tests":7740,"TOTAL_Tests":7950,"NEW_Tests":268,"TOTAL_Cases":189,"NEW_Cases":33,"TOTAL_Recovered":78,"NEW_Recovered":2,"TOTAL_Deaths":0,"NEW_Deaths":0,"TOTAL_Active":111,"NEW_Active":31,"TOTAL_Confirmed":173,"NEW_Confirmed":31,"NEW_Hospitalized":1,"TOTAL_Hospitalized":11,"TOTAL_Probable":16,"NEW_Probable":2}},{"attributes":{"OBJECTID":62,"NAME":"Robertson","Shape__Area":0.124168689004364,"Shape__Length":1.76752725952718,"County":"Robertson","POS_Tests":1519,"NEG_Tests":8576,"TOTAL_Tests":10095,"NEW_Tests":181,"TOTAL_Cases":1197,"NEW_Cases":13,"TOTAL_Recovered":681,"NEW_Recovered":11,"TOTAL_Deaths":16,"NEW_Deaths":1,"TOTAL_Active":500,"NEW_Active":1,"TOTAL_Confirmed":1196,"NEW_Confirmed":13,"NEW_Hospitalized":3,"TOTAL_Hospitalized":71,"TOTAL_Probable":1,"NEW_Probable":0}},{"attributes":{"OBJECTID":7,"NAME":"Rutherford","Shape__Area":0.161242114886818,"Shape__Length":2.51150966229581,"County":"Rutherford","POS_Tests":6068,"NEG_Tests":36820,"TOTAL_Tests":42888,"NEW_Tests":1740,"TOTAL_Cases":5016,"NEW_Cases":188,"TOTAL_Recovered":2371,"NEW_Recovered":104,"TOTAL_Deaths":45,"NEW_Deaths":2,"TOTAL_Active":2600,"NEW_Active":82,"TOTAL_Confirmed":5009,"NEW_Confirmed":188,"NEW_Hospitalized":4,"TOTAL_Hospitalized":156,"TOTAL_Probable":7,"NEW_Probable":0}},{"attributes":{"OBJECTID":90,"NAME":"Scott","Shape__Area":0.138790440789307,"Shape__Length":1.97727826925288,"County":"Scott","POS_Tests":38,"NEG_Tests":1662,"TOTAL_Tests":1700,"NEW_Tests":46,"TOTAL_Cases":39,"NEW_Cases":0,"TOTAL_Recovered":24,"NEW_Recovered":0,"TOTAL_Deaths":0,"NEW_Deaths":0,"TOTAL_Active":15,"NEW_Active":0,"TOTAL_Confirmed":36,"NEW_Confirmed":0,"NEW_Hospitalized":0,"TOTAL_Hospitalized":3,"TOTAL_Probable":3,"NEW_Probable":0}},{"attributes":{"OBJECTID":43,"NAME":"Sequatchie","Shape__Area":0.0683429613770841,"Shape__Length":1.47764424873645,"County":"Sequatchie","POS_Tests":86,"NEG_Tests":2300,"TOTAL_Tests":2386,"NEW_Tests":44,"TOTAL_Cases":69,"NEW_Cases":1,"TOTAL_Recovered":44,"NEW_Recovered":1,"TOTAL_Deaths":0,"NEW_Deaths":0,"TOTAL_Active":25,"NEW_Active":0,"TOTAL_Confirmed":69,"NEW_Confirmed":1,"NEW_Hospitalized":0,"TOTAL_Hospitalized":3,"TOTAL_Probable":0,"NEW_Probable":0}},{"attributes":{"OBJECTID":74,"NAME":"Sevier","Shape__Area":0.154323467372478,"Shape__Length":2.15221391468396,"County":"Sevier","POS_Tests":1349,"NEG_Tests":13239,"TOTAL_Tests":14588,"NEW_Tests":576,"TOTAL_Cases":1269,"NEW_Cases":95,"TOTAL_Recovered":867,"NEW_Recovered":20,"TOTAL_Deaths":4,"NEW_Deaths":0,"TOTAL_Active":398,"NEW_Active":75,"TOTAL_Confirmed":1216,"NEW_Confirmed":94,"NEW_Hospitalized":0,"TOTAL_Hospitalized":43,"TOTAL_Probable":53,"NEW_Probable":1}},{"attributes":{"OBJECTID":66,"NAME":"Shelby","Shape__Area":0.20120538094443,"Shape__Length":2.40357326657517,"County":"Shelby","POS_Tests":20857,"NEG_Tests":190009,"TOTAL_Tests":210866,"NEW_Tests":3577,"TOTAL_Cases":17278,"NEW_Cases":312,"TOTAL_Recovered":12473,"NEW_Recovered":371,"TOTAL_Deaths":260,"NEW_Deaths":3,"TOTAL_Active":4545,"NEW_Active":-62,"TOTAL_Confirmed":17245,"NEW_Confirmed":313,"NEW_Hospitalized":21,"TOTAL_Hospitalized":1126,"TOTAL_Probable":33,"NEW_Probable":-1}},{"attributes":{"OBJECTID":8,"NAME":"Smith","Shape__Area":0.0844980617014244,"Shape__Length":1.59973886739663,"County":"Smith","POS_Tests":295,"NEG_Tests":2655,"TOTAL_Tests":2950,"NEW_Tests":117,"TOTAL_Cases":268,"NEW_Cases":7,"TOTAL_Recovered":143,"NEW_Recovered":8,"TOTAL_Deaths":2,"NEW_Deaths":0,"TOTAL_Active":123,"NEW_Active":-1,"TOTAL_Confirmed":261,"NEW_Confirmed":7,"NEW_Hospitalized":0,"TOTAL_Hospitalized":9,"TOTAL_Probable":7,"NEW_Probable":0}},{"attributes":{"OBJECTID":33,"NAME":"Stewart","Shape__Area":0.128439554426677,"Shape__Length":1.5213361107467,"County":"Stewart","POS_Tests":60,"NEG_Tests":1199,"TOTAL_Tests":1259,"NEW_Tests":37,"TOTAL_Cases":50,"NEW_Cases":2,"TOTAL_Recovered":15,"NEW_Recovered":1,"TOTAL_Deaths":0,"NEW_Deaths":0,"TOTAL_Active":35,"NEW_Active":1,"TOTAL_Confirmed":50,"NEW_Confirmed":2,"NEW_Hospitalized":0,"TOTAL_Hospitalized":3,"TOTAL_Probable":0,"NEW_Probable":0}},{"attributes":{"OBJECTID":30,"NAME":"Sullivan","Shape__Area":0.111963658894638,"Shape__Length":2.21887619882262,"County":"Sullivan","POS_Tests":515,"NEG_Tests":10822,"TOTAL_Tests":11337,"NEW_Tests":919,"TOTAL_Cases":489,"NEW_Cases":32,"TOTAL_Recovered":279,"NEW_Recovered":31,"TOTAL_Deaths":6,"NEW_Deaths":0,"TOTAL_Active":204,"NEW_Active":1,"TOTAL_Confirmed":441,"NEW_Confirmed":30,"NEW_Hospitalized":2,"TOTAL_Hospitalized":36,"TOTAL_Probable":48,"NEW_Probable":2}},{"attributes":{"OBJECTID":10,"NAME":"Sumner","Shape__Area":0.141461816347373,"Shape__Length":1.97192762861997,"County":"Sumner","POS_Tests":3319,"NEG_Tests":20671,"TOTAL_Tests":23990,"NEW_Tests":435,"TOTAL_Cases":2721,"NEW_Cases":51,"TOTAL_Recovered":1172,"NEW_Recovered":51,"TOTAL_Deaths":65,"NEW_Deaths":3,"TOTAL_Active":1484,"NEW_Active":-3,"TOTAL_Confirmed":2709,"NEW_Confirmed":50,"NEW_Hospitalized":5,"TOTAL_Hospitalized":262,"TOTAL_Probable":12,"NEW_Probable":1}},{"attributes":{"OBJECTID":82,"NAME":"Tipton","Shape__Area":0.121774419441181,"Shape__Length":2.65125890147379,"County":"Tipton","POS_Tests":975,"NEG_Tests":10541,"TOTAL_Tests":11516,"NEW_Tests":264,"TOTAL_Cases":877,"NEW_Cases":37,"TOTAL_Recovered":591,"NEW_Recovered":12,"TOTAL_Deaths":8,"NEW_Deaths":0,"TOTAL_Active":278,"NEW_Active":25,"TOTAL_Confirmed":866,"NEW_Confirmed":37,"NEW_Hospitalized":1,"TOTAL_Hospitalized":41,"TOTAL_Probable":11,"NEW_Probable":0}},{"attributes":{"OBJECTID":9,"NAME":"Trousdale","Shape__Area":0.0303458505186427,"Shape__Length":0.997603096912578,"County":"Trousdale","POS_Tests":1612,"NEG_Tests":2952,"TOTAL_Tests":4564,"NEW_Tests":47,"TOTAL_Cases":1556,"NEW_Cases":8,"TOTAL_Recovered":1462,"NEW_Recovered":4,"TOTAL_Deaths":6,"NEW_Deaths":0,"TOTAL_Active":88,"NEW_Active":4,"TOTAL_Confirmed":1553,"NEW_Confirmed":8,"NEW_Hospitalized":0,"TOTAL_Hospitalized":16,"TOTAL_Probable":3,"NEW_Probable":0}},{"attributes":{"OBJECTID":49,"NAME":"Unicoi","Shape__Area":0.0483180558237564,"Shape__Length":1.24501456200437,"County":"Unicoi","POS_Tests":83,"NEG_Tests":2280,"TOTAL_Tests":2363,"NEW_Tests":78,"TOTAL_Cases":77,"NEW_Cases":2,"TOTAL_Recovered":57,"NEW_Recovered":1,"TOTAL_Deaths":0,"NEW_Deaths":0,"TOTAL_Active":20,"NEW_Active":1,"TOTAL_Confirmed":76,"NEW_Confirmed":2,"NEW_Hospitalized":0,"TOTAL_Hospitalized":2,"TOTAL_Probable":1,"NEW_Probable":0}},{"attributes":{"OBJECTID":25,"NAME":"Union","Shape__Area":0.0642108392039518,"Shape__Length":1.37862649202538,"County":"Union","POS_Tests":63,"NEG_Tests":1707,"TOTAL_Tests":1770,"NEW_Tests":43,"TOTAL_Cases":61,"NEW_Cases":2,"TOTAL_Recovered":28,"NEW_Recovered":1,"TOTAL_Deaths":0,"NEW_Deaths":0,"TOTAL_Active":33,"NEW_Active":1,"TOTAL_Confirmed":61,"NEW_Confirmed":2,"NEW_Hospitalized":0,"TOTAL_Hospitalized":1,"TOTAL_Probable":0,"NEW_Probable":0}},{"attributes":{"OBJECTID":39,"NAME":"Van Buren","Shape__Area":0.0708046546333208,"Shape__Length":1.38119613890504,"County":"Van Buren","POS_Tests":20,"NEG_Tests":646,"TOTAL_Tests":666,"NEW_Tests":17,"TOTAL_Cases":19,"NEW_Cases":4,"TOTAL_Recovered":6,"NEW_Recovered":0,"TOTAL_Deaths":0,"NEW_Deaths":0,"TOTAL_Active":13,"NEW_Active":4,"TOTAL_Confirmed":19,"NEW_Confirmed":4,"NEW_Hospitalized":0,"TOTAL_Hospitalized":1,"TOTAL_Probable":0,"NEW_Probable":0}},{"attributes":{"OBJECTID":19,"NAME":"Warren","Shape__Area":0.111918078821418,"Shape__Length":1.62523460705255,"County":"Warren","POS_Tests":286,"NEG_Tests":5600,"TOTAL_Tests":5886,"NEW_Tests":189,"TOTAL_Cases":262,"NEW_Cases":14,"TOTAL_Recovered":95,"NEW_Recovered":8,"TOTAL_Deaths":3,"NEW_Deaths":0,"TOTAL_Active":164,"NEW_Active":6,"TOTAL_Confirmed":262,"NEW_Confirmed":14,"NEW_Hospitalized":0,"TOTAL_Hospitalized":2,"TOTAL_Probable":0,"NEW_Probable":0}},{"attributes":{"OBJECTID":32,"NAME":"Washington","Shape__Area":0.0857003142364192,"Shape__Length":1.54126323705726,"County":"Washington","POS_Tests":616,"NEG_Tests":11099,"TOTAL_Tests":11715,"NEW_Tests":657,"TOTAL_Cases":523,"NEW_Cases":21,"TOTAL_Recovered":171,"NEW_Recovered":1,"TOTAL_Deaths":0,"NEW_Deaths":0,"TOTAL_Active":352,"NEW_Active":20,"TOTAL_Confirmed":508,"NEW_Confirmed":21,"NEW_Hospitalized":1,"TOTAL_Hospitalized":24,"TOTAL_Probable":15,"NEW_Probable":0}},{"attributes":{"OBJECTID":37,"NAME":"Wayne","Shape__Area":0.188680579656193,"Shape__Length":2.01680044059484,"County":"Wayne","POS_Tests":178,"NEG_Tests":3306,"TOTAL_Tests":3484,"NEW_Tests":62,"TOTAL_Cases":169,"NEW_Cases":10,"TOTAL_Recovered":94,"NEW_Recovered":2,"TOTAL_Deaths":0,"NEW_Deaths":0,"TOTAL_Active":75,"NEW_Active":8,"TOTAL_Confirmed":168,"NEW_Confirmed":10,"NEW_Hospitalized":1,"TOTAL_Hospitalized":5,"TOTAL_Probable":1,"NEW_Probable":0}},{"attributes":{"OBJECTID":71,"NAME":"Weakley","Shape__Area":0.151178288340134,"Shape__Length":1.94068947426386,"County":"Weakley","POS_Tests":128,"NEG_Tests":3579,"TOTAL_Tests":3707,"NEW_Tests":176,"TOTAL_Cases":123,"NEW_Cases":14,"TOTAL_Recovered":54,"NEW_Recovered":0,"TOTAL_Deaths":1,"NEW_Deaths":0,"TOTAL_Active":68,"NEW_Active":14,"TOTAL_Confirmed":118,"NEW_Confirmed":14,"NEW_Hospitalized":0,"TOTAL_Hospitalized":4,"TOTAL_Probable":5,"NEW_Probable":0}},{"attributes":{"OBJECTID":3,"NAME":"White","Shape__Area":0.098136800682596,"Shape__Length":1.87046293137068,"County":"White","POS_Tests":174,"NEG_Tests":3673,"TOTAL_Tests":3847,"NEW_Tests":69,"TOTAL_Cases":145,"NEW_Cases":7,"TOTAL_Recovered":80,"NEW_Recovered":5,"TOTAL_Deaths":3,"NEW_Deaths":0,"TOTAL_Active":62,"NEW_Active":2,"TOTAL_Confirmed":144,"NEW_Confirmed":7,"NEW_Hospitalized":0,"TOTAL_Hospitalized":9,"TOTAL_Probable":1,"NEW_Probable":0}},{"attributes":{"OBJECTID":52,"NAME":"Williamson","Shape__Area":0.150926713067975,"Shape__Length":2.1113023128171,"County":"Williamson","POS_Tests":3192,"NEG_Tests":32712,"TOTAL_Tests":35904,"NEW_Tests":597,"TOTAL_Cases":2717,"NEW_Cases":69,"TOTAL_Recovered":1232,"NEW_Recovered":73,"TOTAL_Deaths":21,"NEW_Deaths":2,"TOTAL_Active":1464,"NEW_Active":-6,"TOTAL_Confirmed":2714,"NEW_Confirmed":69,"NEW_Hospitalized":1,"TOTAL_Hospitalized":71,"TOTAL_Probable":3,"NEW_Probable":0}},{"attributes":{"OBJECTID":63,"NAME":"Wilson","Shape__Area":0.151330742676691,"Shape__Length":2.2855044285423,"County":"Wilson","POS_Tests":2103,"NEG_Tests":18781,"TOTAL_Tests":20884,"NEW_Tests":660,"TOTAL_Cases":1746,"NEW_Cases":58,"TOTAL_Recovered":897,"NEW_Recovered":66,"TOTAL_Deaths":20,"NEW_Deaths":1,"TOTAL_Active":829,"NEW_Active":-9,"TOTAL_Confirmed":1744,"NEW_Confirmed":58,"NEW_Hospitalized":1,"TOTAL_Hospitalized":67,"TOTAL_Probable":2,"NEW_Probable":0}}]}