{"objectIdFieldName":"OBJECTID","uniqueIdField":{"name":"OBJECTID","isSystemMaintained":true},"globalIdFieldName":"","geometryType":"esriGeometryPolygon","spatialReference":{"wkid":102100,"latestWkid":3857},"fields":[{"name":"OBJECTID","type":"esriFieldTypeOID","alias":"OBJECTID","sqlType":"sqlTypeInteger","domain":null,"defaultValue":null},{"name":"NAME","type":"esriFieldTypeString","alias":"Name","sqlType":"sqlTypeNVarchar","length":32,"domain":null,"defaultValue":null},{"name":"NAMELABEL","type":"esriFieldTypeString","alias":"Name Label","sqlType":"sqlTypeNVarchar","length":32,"domain":null,"defaultValue":null},{"name":"NAMEABBR","type":"esriFieldTypeString","alias":"Name Abbreviation","sqlType":"sqlTypeNVarchar","length":3,"domain":null,"defaultValue":null},{"name":"COUNTYNUMBER","type":"esriFieldTypeSmallInteger","alias":"County Number","sqlType":"sqlTypeSmallInt","domain":null,"defaultValue":null},{"name":"PKEY","type":"esriFieldTypeString","alias":"Unique ID","sqlType":"sqlTypeNVarchar","length":35,"domain":null,"defaultValue":null},{"name":"SQMILES","type":"esriFieldTypeDouble","alias":"Square Miles","sqlType":"sqlTypeDecimal","domain":null,"defaultValue":null},{"name":"PERIMETER","type":"esriFieldTypeDouble","alias":"Perimeter (Miles)","sqlType":"sqlTypeDecimal","domain":null,"defaultValue":null},{"name":"ACRES","type":"esriFieldTypeDouble","alias":"Acres","sqlType":"sqlTypeDecimal","domain":null,"defaultValue":null},{"name":"ALLFIPS","type":"esriFieldTypeString","alias":"STATE/FIPS/ANSI CODE","sqlType":"sqlTypeNVarchar","length":5,"domain":null,"defaultValue":null},{"name":"FIPS","type":"esriFieldTypeString","alias":"FIPS/ANSI CODE","sqlType":"sqlTypeNVarchar","length":3,"domain":null,"defaultValue":null},{"name":"LAST_UPDATE","type":"esriFieldTypeDate","alias":"Last Updated","sqlType":"sqlTypeTimestamp2","length":8,"domain":null,"defaultValue":null},{"name":"GLOBALID","type":"esriFieldTypeGUID","alias":"GLOBALID","sqlType":"sqlTypeGUID","length":16,"domain":null,"defaultValue":null},{"name":"Total","type":"esriFieldTypeInteger","alias":"Total","sqlType":"sqlTypeInteger","domain":null,"defaultValue":null},{"name":"F_0_9","type":"esriFieldTypeInteger","alias":"F_0_9","sqlType":"sqlTypeInteger","domain":null,"defaultValue":null},{"name":"M_0_9","type":"esriFieldTypeInteger","alias":"M_0_9","sqlType":"sqlTypeInteger","domain":null,"defaultValue":null},{"name":"T_0_9","type":"esriFieldTypeInteger","alias":"T_0_9","sqlType":"sqlTypeInteger","domain":null,"defaultValue":null},{"name":"F_10_19","type":"esriFieldTypeInteger","alias":"F_10_19","sqlType":"sqlTypeInteger","domain":null,"defaultValue":null},{"name":"M_10_19","type":"esriFieldTypeInteger","alias":"M_10_19","sqlType":"sqlTypeInteger","domain":null,"defaultValue":null},{"name":"T_10_19","type":"esriFieldTypeInteger","alias":"T_10_19","sqlType":"sqlTypeInteger","domain":null,"defaultValue":null},{"name":"F_20_29","type":"esriFieldTypeInteger","alias":"F_20_29","sqlType":"sqlTypeInteger","domain":null,"defaultValue":null},{"name":"M_20_29","type":"esriFieldTypeInteger","alias":"M_20_29","sqlType":"sqlTypeInteger","domain":null,"defaultValue":null},{"name":"T_20_29","type":"esriFieldTypeInteger","alias":"T_20_29","sqlType":"sqlTypeInteger","domain":null,"defaultValue":null},{"name":"F_30_39","type":"esriFieldTypeInteger","alias":"F_30-39","sqlType":"sqlTypeInteger","domain":null,"defaultValue":null},{"name":"M_30_39","type":"esriFieldTypeInteger","alias":"M_30-39","sqlType":"sqlTypeInteger","domain":null,"defaultValue":null},{"name":"T_30_39","type":"esriFieldTypeInteger","alias":"T_30-39","sqlType":"sqlTypeInteger","domain":null,"defaultValue":null},{"name":"F_40_49","type":"esriFieldTypeInteger","alias":"F_40-49","sqlType":"sqlTypeInteger","domain":null,"defaultValue":null},{"name":"M_40_49","type":"esriFieldTypeInteger","alias":"M_40-49","sqlType":"sqlTypeInteger","domain":null,"defaultValue":null},{"name":"T_40_49","type":"esriFieldTypeInteger","alias":"T_40-49","sqlType":"sqlTypeInteger","domain":null,"defaultValue":null},{"name":"F_50_59","type":"esriFieldTypeInteger","alias":"F_50-59","sqlType":"sqlTypeInteger","domain":null,"defaultValue":null},{"name":"M_50_59","type":"esriFieldTypeInteger","alias":"M_50-59","sqlType":"sqlTypeInteger","domain":null,"defaultValue":null},{"name":"T_50_59","type":"esriFieldTypeInteger","alias":"T_50-59","sqlType":"sqlTypeInteger","domain":null,"defaultValue":null},{"name":"F_60_69","type":"esriFieldTypeInteger","alias":"F_60-69","sqlType":"sqlTypeInteger","domain":null,"defaultValue":null},{"name":"M_60_69","type":"esriFieldTypeInteger","alias":"M_60-69","sqlType":"sqlTypeInteger","domain":null,"defaultValue":null},{"name":"T_60_69","type":"esriFieldTypeInteger","alias":"T_60-69","sqlType":"sqlTypeInteger","domain":null,"defaultValue":null},{"name":"F_70_79","type":"esriFieldTypeInteger","alias":"F_70-79","sqlType":"sqlTypeInteger","domain":null,"defaultValue":null},{"name":"M_70_79","type":"esriFieldTypeInteger","alias":"M_70-79","sqlType":"sqlTypeInteger","domain":null,"defaultValue":null},{"name":"T_70_79","type":"esriFieldTypeInteger","alias":"T_70-79","sqlType":"sqlTypeInteger","domain":null,"defaultValue":null},{"name":"F_80_89","type":"esriFieldTypeInteger","alias":"F_80-89","sqlType":"sqlTypeInteger","domain":null,"defaultValue":null},{"name":"M_80_89","type":"esriFieldTypeInteger","alias":"M_80-89","sqlType":"sqlTypeInteger","domain":null,"defaultValue":null},{"name":"T_80_89","type":"esriFieldTypeInteger","alias":"T_80-89","sqlType":"sqlTypeInteger","domain":null,"defaultValue":null},{"name":"F_90_99","type":"esriFieldTypeInteger","alias":"F_90-99","sqlType":"sqlTypeInteger","domain":null,"defaultValue":null},{"name":"M_90_99","type":"esriFieldTypeInteger","alias":"M_90-99","sqlType":"sqlTypeInteger","domain":null,"defaultValue":null},{"name":"T_90_99","type":"esriFieldTypeInteger","alias":"T_90-99","sqlType":"sqlTypeInteger","domain":null,"defaultValue":null},{"name":"F_100","type":"esriFieldTypeInteger","alias":"F_100","sqlType":"sqlTypeInteger","domain":null,"defaultValue":null},{"name":"M_100","type":"esriFieldTypeInteger","alias":"M_100","sqlType":"sqlTypeInteger","domain":null,"defaultValue":null},{"name":"T_100","type":"esriFieldTypeInteger","alias":"T_100","sqlType":"sqlTypeInteger","domain":null,"defaultValue":null},{"name":"Notes","type":"esriFieldTypeString","alias":"Notes","sqlType":"sqlTypeNVarchar","length":255,"domain":null,"defaultValue":null}],"features":[{"attributes":{"OBJECTID":21,"NAME":"BROADWATER","NAMELABEL":"Broadwater","NAMEABBR":"BR","COUNTYNUMBER":43,"PKEY":"306101002.BND.43","SQMILES":1238.12384664,"PERIMETER":208.94926718,"ACRES":792399.26174422,"ALLFIPS":"30007","FIPS":"007","LAST_UPDATE":1441756800000,"GLOBALID":"f433da8e-2cfd-48e5-b2b0-79addc17730c","Total":1,"F_0_9":0,"M_0_9":0,"T_0_9":0,"F_10_19":0,"M_10_19":0,"T_10_19":0,"F_20_29":0,"M_20_29":0,"T_20_29":0,"F_30_39":0,"M_30_39":0,"T_30_39":0,"F_40_49":0,"M_40_49":0,"T_40_49":0,"F_50_59":0,"M_50_59":1,"T_50_59":1,"F_60_69":0,"M_60_69":0,"T_60_69":0,"F_70_79":0,"M_70_79":0,"T_70_79":0,"F_80_89":0,"M_80_89":0,"T_80_89":0,"F_90_99":0,"M_90_99":0,"T_90_99":0,"F_100":0,"M_100":0,"T_100":0,"Notes":null}},{"attributes":{"OBJECTID":33,"NAME":"CASCADE","NAMELABEL":"Cascade","NAMEABBR":"CS","COUNTYNUMBER":2,"PKEY":"306101002.BND.2","SQMILES":2711.53169069,"PERIMETER":314.32120647,"ACRES":1735380.28181674,"ALLFIPS":"30013","FIPS":"013","LAST_UPDATE":1427760000000,"GLOBALID":"2aaecd9d-adf1-4442-952e-d704d11335a7","Total":3,"F_0_9":0,"M_0_9":0,"T_0_9":0,"F_10_19":0,"M_10_19":0,"T_10_19":0,"F_20_29":1,"M_20_29":0,"T_20_29":1,"F_30_39":0,"M_30_39":0,"T_30_39":0,"F_40_49":0,"M_40_49":0,"T_40_49":0,"F_50_59":1,"M_50_59":1,"T_50_59":2,"F_60_69":0,"M_60_69":0,"T_60_69":0,"F_70_79":0,"M_70_79":0,"T_70_79":0,"F_80_89":0,"M_80_89":0,"T_80_89":0,"F_90_99":0,"M_90_99":0,"T_90_99":0,"F_100":0,"M_100":0,"T_100":0,"Notes":null}},{"attributes":{"OBJECTID":52,"NAME":"FLATHEAD","NAMELABEL":"Flathead","NAMEABBR":"FL","COUNTYNUMBER":7,"PKEY":"306101002.BND.7","SQMILES":5256.03388725,"PERIMETER":486.66009221,"ACRES":3363861.6874051,"ALLFIPS":"30029","FIPS":"029","LAST_UPDATE":1549497600000,"GLOBALID":"76c53290-a60e-429b-9cd0-40bef0a5d451","Total":4,"F_0_9":0,"M_0_9":0,"T_0_9":0,"F_10_19":0,"M_10_19":0,"T_10_19":0,"F_20_29":0,"M_20_29":0,"T_20_29":0,"F_30_39":1,"M_30_39":1,"T_30_39":2,"F_40_49":0,"M_40_49":0,"T_40_49":0,"F_50_59":0,"M_50_59":2,"T_50_59":2,"F_60_69":0,"M_60_69":0,"T_60_69":0,"F_70_79":0,"M_70_79":0,"T_70_79":0,"F_80_89":0,"M_80_89":0,"T_80_89":0,"F_90_99":0,"M_90_99":0,"T_90_99":0,"F_100":0,"M_100":0,"T_100":0,"Notes":"One reported case of an out of state resident, male 50-59"}},{"attributes":{"OBJECTID":8,"NAME":"GALLATIN","NAMELABEL":"Gallatin","NAMEABBR":"GA","COUNTYNUMBER":6,"PKEY":"306101002.BND.6","SQMILES":2633.88684521,"PERIMETER":337.38453045,"ACRES":1685687.58071298,"ALLFIPS":"30031","FIPS":"031","LAST_UPDATE":1549497600000,"GLOBALID":"b15dd584-4299-4fcf-be77-8a4423a41833","Total":19,"F_0_9":0,"M_0_9":0,"T_0_9":0,"F_10_19":1,"M_10_19":1,"T_10_19":2,"F_20_29":1,"M_20_29":2,"T_20_29":3,"F_30_39":1,"M_30_39":2,"T_30_39":3,"F_40_49":1,"M_40_49":1,"T_40_49":2,"F_50_59":2,"M_50_59":1,"T_50_59":3,"F_60_69":0,"M_60_69":5,"T_60_69":5,"F_70_79":1,"M_70_79":0,"T_70_79":1,"F_80_89":0,"M_80_89":0,"T_80_89":0,"F_90_99":0,"M_90_99":0,"T_90_99":0,"F_100":0,"M_100":0,"T_100":0,"Notes":"Male in 60s is California resident, Male in 20s is New Hampshire resident"}},{"attributes":{"OBJECTID":15,"NAME":"JEFFERSON","NAMELABEL":"Jefferson","NAMEABBR":"JE","COUNTYNUMBER":51,"PKEY":"306101002.BND.51","SQMILES":1659.41805021,"PERIMETER":216.61245334,"ACRES":1062027.55199685,"ALLFIPS":"30043","FIPS":"043","LAST_UPDATE":1441756800000,"GLOBALID":"8be5fc81-bd64-4613-a5af-68759a8a09f7","Total":1,"F_0_9":0,"M_0_9":0,"T_0_9":0,"F_10_19":0,"M_10_19":0,"T_10_19":0,"F_20_29":0,"M_20_29":0,"T_20_29":0,"F_30_39":0,"M_30_39":0,"T_30_39":0,"F_40_49":0,"M_40_49":0,"T_40_49":0,"F_50_59":0,"M_50_59":1,"T_50_59":1,"F_60_69":0,"M_60_69":0,"T_60_69":0,"F_70_79":0,"M_70_79":0,"T_70_79":0,"F_80_89":0,"M_80_89":0,"T_80_89":0,"F_90_99":0,"M_90_99":0,"T_90_99":0,"F_100":0,"M_100":0,"T_100":0,"Notes":null}},{"attributes":{"OBJECTID":35,"NAME":"LEWIS AND CLARK","NAMELABEL":"Lewis and Clark","NAMEABBR":"LC","COUNTYNUMBER":5,"PKEY":"306101002.BND.5","SQMILES":3497.57736587,"PERIMETER":403.17696545,"ACRES":2238449.51386785,"ALLFIPS":"30049","FIPS":"049","LAST_UPDATE":1549497600000,"GLOBALID":"45a17b74-b2b2-4c15-b547-bb003966ff8d","Total":3,"F_0_9":0,"M_0_9":0,"T_0_9":0,"F_10_19":0,"M_10_19":1,"T_10_19":1,"F_20_29":0,"M_20_29":0,"T_20_29":0,"F_30_39":0,"M_30_39":1,"T_30_39":1,"F_40_49":1,"M_40_49":0,"T_40_49":1,"F_50_59":0,"M_50_59":0,"T_50_59":0,"F_60_69":0,"M_60_69":0,"T_60_69":0,"F_70_79":0,"M_70_79":0,"T_70_79":0,"F_80_89":0,"M_80_89":0,"T_80_89":0,"F_90_99":0,"M_90_99":0,"T_90_99":0,"F_100":0,"M_100":0,"T_100":0,"Notes":null}},{"attributes":{"OBJECTID":3,"NAME":"MADISON","NAMELABEL":"Madison","NAMEABBR":"MA","COUNTYNUMBER":25,"PKEY":"306101002.BND.25","SQMILES":3603.46154607,"PERIMETER":290.32843386,"ACRES":2306215.38918553,"ALLFIPS":"30057","FIPS":"057","LAST_UPDATE":1549497600000,"GLOBALID":"e89e9320-1ee7-47aa-974f-3dec273c6fd0","Total":1,"F_0_9":0,"M_0_9":0,"T_0_9":0,"F_10_19":0,"M_10_19":0,"T_10_19":0,"F_20_29":0,"M_20_29":0,"T_20_29":0,"F_30_39":0,"M_30_39":0,"T_30_39":0,"F_40_49":0,"M_40_49":0,"T_40_49":0,"F_50_59":1,"M_50_59":0,"T_50_59":1,"F_60_69":0,"M_60_69":0,"T_60_69":0,"F_70_79":0,"M_70_79":0,"T_70_79":0,"F_80_89":0,"M_80_89":0,"T_80_89":0,"F_90_99":0,"M_90_99":0,"T_90_99":0,"F_100":0,"M_100":0,"T_100":0,"Notes":null}},{"attributes":{"OBJECTID":32,"NAME":"MISSOULA","NAMELABEL":"Missoula","NAMEABBR":"MS","COUNTYNUMBER":4,"PKEY":"306101002.BND.4","SQMILES":2617.98390163,"PERIMETER":342.56268949,"ACRES":1675509.69682839,"ALLFIPS":"30063","FIPS":"063","LAST_UPDATE":1549497600000,"GLOBALID":"55680878-5841-4495-b86b-ea4903cbf357","Total":6,"F_0_9":0,"M_0_9":0,"T_0_9":0,"F_10_19":0,"M_10_19":0,"T_10_19":0,"F_20_29":0,"M_20_29":1,"T_20_29":1,"F_30_39":1,"M_30_39":0,"T_30_39":1,"F_40_49":0,"M_40_49":0,"T_40_49":0,"F_50_59":0,"M_50_59":2,"T_50_59":2,"F_60_69":1,"M_60_69":1,"T_60_69":2,"F_70_79":0,"M_70_79":0,"T_70_79":0,"F_80_89":0,"M_80_89":0,"T_80_89":0,"F_90_99":0,"M_90_99":0,"T_90_99":0,"F_100":0,"M_100":0,"T_100":0,"Notes":null}},{"attributes":{"OBJECTID":18,"NAME":"RAVALLI","NAMELABEL":"Ravalli","NAMEABBR":"RA","COUNTYNUMBER":13,"PKEY":"306101002.BND.13","SQMILES":2400.3898636,"PERIMETER":315.24679481,"ACRES":1536249.51250318,"ALLFIPS":"30081","FIPS":"081","LAST_UPDATE":1262217600000,"GLOBALID":"ae974f59-2dfb-4eaa-8adc-12cbb2ab5fa1","Total":1,"F_0_9":0,"M_0_9":0,"T_0_9":0,"F_10_19":1,"M_10_19":0,"T_10_19":1,"F_20_29":0,"M_20_29":0,"T_20_29":0,"F_30_39":0,"M_30_39":0,"T_30_39":0,"F_40_49":0,"M_40_49":0,"T_40_49":0,"F_50_59":0,"M_50_59":0,"T_50_59":0,"F_60_69":0,"M_60_69":0,"T_60_69":0,"F_70_79":0,"M_70_79":0,"T_70_79":0,"F_80_89":0,"M_80_89":0,"T_80_89":0,"F_90_99":0,"M_90_99":0,"T_90_99":0,"F_100":0,"M_100":0,"T_100":0,"Notes":null}},{"attributes":{"OBJECTID":43,"NAME":"ROOSEVELT","NAMELABEL":"Roosevelt","NAMEABBR":"RO","COUNTYNUMBER":17,"PKEY":"306101002.BND.17","SQMILES":2368.82950093,"PERIMETER":294.25073765,"ACRES":1516050.88039888,"ALLFIPS":"30085","FIPS":"085","LAST_UPDATE":1476489600000,"GLOBALID":"5fa279c4-5c3c-4515-9a9d-0982942f5bb8","Total":1,"F_0_9":0,"M_0_9":0,"T_0_9":0,"F_10_19":0,"M_10_19":0,"T_10_19":0,"F_20_29":0,"M_20_29":0,"T_20_29":0,"F_30_39":0,"M_30_39":0,"T_30_39":0,"F_40_49":0,"M_40_49":0,"T_40_49":0,"F_50_59":0,"M_50_59":0,"T_50_59":0,"F_60_69":0,"M_60_69":0,"T_60_69":0,"F_70_79":1,"M_70_79":0,"T_70_79":1,"F_80_89":0,"M_80_89":0,"T_80_89":0,"F_90_99":0,"M_90_99":0,"T_90_99":0,"F_100":0,"M_100":0,"T_100":0,"Notes":null}},{"attributes":{"OBJECTID":10,"NAME":"SILVER BOW","NAMELABEL":"Silver Bow","NAMEABBR":"SB","COUNTYNUMBER":1,"PKEY":"306101002.BND.1","SQMILES":718.57606325,"PERIMETER":159.87338936,"ACRES":459888.68041839,"ALLFIPS":"30093","FIPS":"093","LAST_UPDATE":1262217600000,"GLOBALID":"6b5df3f8-7ee6-48d2-a764-8ccee5f3de75","Total":3,"F_0_9":0,"M_0_9":0,"T_0_9":0,"F_10_19":0,"M_10_19":0,"T_10_19":0,"F_20_29":0,"M_20_29":0,"T_20_29":0,"F_30_39":0,"M_30_39":0,"T_30_39":0,"F_40_49":0,"M_40_49":0,"T_40_49":0,"F_50_59":0,"M_50_59":1,"T_50_59":1,"F_60_69":1,"M_60_69":1,"T_60_69":2,"F_70_79":0,"M_70_79":0,"T_70_79":0,"F_80_89":0,"M_80_89":0,"T_80_89":0,"F_90_99":0,"M_90_99":0,"T_90_99":0,"F_100":0,"M_100":0,"T_100":0,"Notes":null}},{"attributes":{"OBJECTID":14,"NAME":"YELLOWSTONE","NAMELABEL":"Yellowstone","NAMEABBR":"YE","COUNTYNUMBER":3,"PKEY":"306101002.BND.3","SQMILES":2649.12472908,"PERIMETER":290.83930903,"ACRES":1695439.82639245,"ALLFIPS":"30111","FIPS":"111","LAST_UPDATE":1476489600000,"GLOBALID":"29f7b13c-7189-4cd9-8750-9395b175e8ed","Total":8,"F_0_9":0,"M_0_9":0,"T_0_9":0,"F_10_19":0,"M_10_19":0,"T_10_19":0,"F_20_29":2,"M_20_29":2,"T_20_29":4,"F_30_39":1,"M_30_39":1,"T_30_39":2,"F_40_49":0,"M_40_49":0,"T_40_49":0,"F_50_59":1,"M_50_59":0,"T_50_59":1,"F_60_69":0,"M_60_69":0,"T_60_69":0,"F_70_79":0,"M_70_79":0,"T_70_79":0,"F_80_89":0,"M_80_89":1,"T_80_89":1,"F_90_99":0,"M_90_99":0,"T_90_99":0,"F_100":0,"M_100":0,"T_100":0,"Notes":null}}]}