{"currentVersion":10.7,"id":0,"name":"Cases_wdemographic_current","type":"Feature Layer","serviceItemId":"fc39fee4867b459384098af27f5cfde2","isView":true,"isUpdatableView":false,"isMultiServicesView":true,"sourceSchemaChangesAllowed":false,"displayField":"name","description":"AttributeJoin","copyrightText":"Esri","defaultVisibility":true,"ownershipBasedAccessControlForFeatures":{"allowOthersToQuery":true,"allowOthersToDelete":true,"allowOthersToUpdate":true,"allowAnonymousToQuery":true,"allowAnonymousToUpdate":true,"allowAnonymousToDelete":true},"editingInfo":{"lastEditDate":1586206996817},"relationships":[],"isDataVersioned":false,"supportsAppend":true,"supportsCalculate":true,"supportsASyncCalculate":true,"supportsTruncate":false,"supportsAttachmentsByUploadId":true,"supportsAttachmentsResizing":true,"supportsRollbackOnFailureParameter":true,"supportsStatistics":true,"supportsExceedsLimitStatistics":true,"supportsAdvancedQueries":true,"supportsValidateSql":true,"supportsCoordinatesQuantization":true,"supportsFieldDescriptionProperty":true,"supportsQuantizationEditMode":true,"supportsApplyEditsWithGlobalIds":true,"supportsMultiScaleGeometry":true,"supportsReturningQueryGeometry":true,"hasGeometryProperties":true,"geometryProperties":{"shapeAreaFieldName":"Shape__Area","shapeLengthFieldName":"Shape__Length","units":"esriMeters"},"supportsOBACForAnonymousUsers":true,"advancedQueryCapabilities":{"supportsPagination":true,"supportsPaginationOnAggregatedQueries":true,"supportsQueryRelatedPagination":true,"supportsQueryWithDistance":true,"supportsReturningQueryExtent":true,"supportsStatistics":true,"supportsOrderBy":true,"supportsDistinct":true,"supportsQueryWithResultType":true,"supportsSqlExpression":true,"supportsAdvancedQueryRelated":true,"supportsCountDistinct":true,"supportsPercentileStatistics":true,"supportsLod":true,"supportsQueryWithLodSR":false,"supportedLodTypes":["geohash"],"supportsReturningGeometryCentroid":true,"supportsReturningGeometryProperties":true,"supportsQueryWithDatumTransformation":true,"supportsHavingClause":true,"supportsOutFieldSQLExpression":true,"supportsMaxRecordCountFactor":true,"supportsTopFeaturesQuery":true,"supportsDisjointSpatialRel":true,"supportsQueryWithCacheHint":true},"useStandardizedQueries":true,"geometryType":"esriGeometryPolygon","minScale":0,"maxScale":2311162,"extent":{"xmin":-13359060.8927,"ymin":4745407.7581999972,"xmax":-13266005.7424,"ymax":5160611.9919999987,"spatialReference":{"wkid":102100,"latestWkid":3857}},"drawingInfo":{"renderer":{"type":"simple","symbol":{"color":[130,130,130,0],"outline":{"color":[0,0,0,255],"width":1,"type":"esriSLS","style":"esriSLSSolid"},"type":"esriSFS","style":"esriSFSSolid"}},"transparency":0},"allowGeometryUpdates":true,"hasAttachments":false,"viewSourceHasAttachments":false,"htmlPopupType":"esriServerHTMLPopupTypeAsHTMLText","hasM":false,"hasZ":false,"objectIdField":"ObjectId","uniqueIdField":{"name":"ObjectId","isSystemMaintained":true},"globalIdField":"GlobalID","typeIdField":"","fields":[{"name":"name","type":"esriFieldTypeString","alias":"Name","sqlType":"sqlTypeOther","length":1000,"nullable":true,"editable":true,"domain":null,"defaultValue":null},{"name":"GlobalID","type":"esriFieldTypeGlobalID","alias":"GlobalID","sqlType":"sqlTypeOther","length":38,"nullable":false,"editable":false,"domain":null,"defaultValue":null},{"name":"CreationDate","type":"esriFieldTypeDate","alias":"CreationDate","sqlType":"sqlTypeOther","length":8,"nullable":true,"editable":false,"domain":null,"defaultValue":null},{"name":"Creator","type":"esriFieldTypeString","alias":"Creator","sqlType":"sqlTypeOther","length":128,"nullable":true,"editable":false,"domain":null,"defaultValue":null},{"name":"EditDate","type":"esriFieldTypeDate","alias":"EditDate","sqlType":"sqlTypeOther","length":8,"nullable":true,"editable":false,"domain":null,"defaultValue":null},{"name":"Editor","type":"esriFieldTypeString","alias":"Editor","sqlType":"sqlTypeOther","length":128,"nullable":true,"editable":false,"domain":null,"defaultValue":null},{"name":"Shape__Area","type":"esriFieldTypeDouble","alias":"Shape__Area","sqlType":"sqlTypeOther","nullable":true,"editable":false,"domain":null,"defaultValue":null},{"name":"Shape__Length","type":"esriFieldTypeDouble","alias":"Shape__Length","sqlType":"sqlTypeOther","nullable":true,"editable":false,"domain":null,"defaultValue":null},{"name":"name_1586183643811","type":"esriFieldTypeString","alias":"Name","sqlType":"sqlTypeOther","length":1000,"nullable":true,"editable":true,"domain":null,"defaultValue":null},{"name":"reportdt","type":"esriFieldTypeDate","alias":"Date Reported","sqlType":"sqlTypeOther","length":8,"nullable":true,"editable":true,"domain":null,"defaultValue":null},{"name":"confirmed","type":"esriFieldTypeInteger","alias":"Confirmed","sqlType":"sqlTypeOther","nullable":true,"editable":true,"domain":null,"defaultValue":null},{"name":"recovered","type":"esriFieldTypeInteger","alias":"Recovered","sqlType":"sqlTypeOther","nullable":true,"editable":true,"domain":null,"defaultValue":null},{"name":"deaths","type":"esriFieldTypeInteger","alias":"Deaths","sqlType":"sqlTypeOther","nullable":true,"editable":true,"domain":null,"defaultValue":null},{"name":"active","type":"esriFieldTypeInteger","alias":"Active","sqlType":"sqlTypeOther","nullable":true,"editable":true,"domain":null,"defaultValue":null},{"name":"GlobalID_1586183643811","type":"esriFieldTypeGUID","alias":"GlobalID","sqlType":"sqlTypeOther","length":38,"nullable":false,"editable":false,"domain":null,"defaultValue":null},{"name":"tested","type":"esriFieldTypeInteger","alias":"Tested","sqlType":"sqlTypeOther","nullable":true,"editable":true,"domain":null,"defaultValue":null},{"name":"CreationDate_1586183643811","type":"esriFieldTypeDate","alias":"CreationDate","sqlType":"sqlTypeOther","length":8,"nullable":true,"editable":false,"domain":null,"defaultValue":null},{"name":"Creator_1586183643811","type":"esriFieldTypeString","alias":"Creator","sqlType":"sqlTypeOther","length":128,"nullable":true,"editable":false,"domain":null,"defaultValue":null},{"name":"EditDate_1586183643811","type":"esriFieldTypeDate","alias":"EditDate","sqlType":"sqlTypeOther","length":8,"nullable":true,"editable":false,"domain":null,"defaultValue":null},{"name":"Editor_1586183643811","type":"esriFieldTypeString","alias":"Editor","sqlType":"sqlTypeOther","length":128,"nullable":true,"editable":false,"domain":null,"defaultValue":null},{"name":"Male","type":"esriFieldTypeSmallInteger","alias":"Male","sqlType":"sqlTypeOther","nullable":true,"editable":true,"domain":null,"defaultValue":null},{"name":"Female","type":"esriFieldTypeSmallInteger","alias":"Female","sqlType":"sqlTypeOther","nullable":true,"editable":true,"domain":null,"defaultValue":null},{"name":"Age0to9","type":"esriFieldTypeSmallInteger","alias":"0-9","sqlType":"sqlTypeOther","nullable":true,"editable":true,"domain":null,"defaultValue":null},{"name":"Age10to19","type":"esriFieldTypeSmallInteger","alias":"10-19","sqlType":"sqlTypeOther","nullable":true,"editable":true,"domain":null,"defaultValue":null},{"name":"Age20to29","type":"esriFieldTypeSmallInteger","alias":"20-29","sqlType":"sqlTypeOther","nullable":true,"editable":true,"domain":null,"defaultValue":null},{"name":"Age30to39","type":"esriFieldTypeSmallInteger","alias":"30-39","sqlType":"sqlTypeOther","nullable":true,"editable":true,"domain":null,"defaultValue":null},{"name":"Age40to49","type":"esriFieldTypeSmallInteger","alias":"40-49","sqlType":"sqlTypeOther","nullable":true,"editable":true,"domain":null,"defaultValue":null},{"name":"Age50to59","type":"esriFieldTypeSmallInteger","alias":"50-59","sqlType":"sqlTypeOther","nullable":true,"editable":true,"domain":null,"defaultValue":null},{"name":"Age60to69","type":"esriFieldTypeSmallInteger","alias":"60-69","sqlType":"sqlTypeOther","nullable":true,"editable":true,"domain":null,"defaultValue":null},{"name":"Age70to79","type":"esriFieldTypeSmallInteger","alias":"70-79","sqlType":"sqlTypeOther","nullable":true,"editable":true,"domain":null,"defaultValue":null},{"name":"Age80to89","type":"esriFieldTypeSmallInteger","alias":"80-89","sqlType":"sqlTypeOther","nullable":true,"editable":true,"domain":null,"defaultValue":null},{"name":"Age90to99","type":"esriFieldTypeSmallInteger","alias":"90-99","sqlType":"sqlTypeOther","nullable":true,"editable":true,"domain":null,"defaultValue":null},{"name":"Age100plus","type":"esriFieldTypeSmallInteger","alias":"100+","sqlType":"sqlTypeOther","nullable":true,"editable":true,"domain":null,"defaultValue":null},{"name":"GenderOther","type":"esriFieldTypeSmallInteger","alias":"Other","sqlType":"sqlTypeOther","nullable":true,"editable":true,"domain":null,"defaultValue":null},{"name":"OtherGender","type":"esriFieldTypeString","alias":"Unk","sqlType":"sqlTypeOther","length":15,"nullable":true,"editable":true,"domain":null,"defaultValue":null},{"name":"AgeNA","type":"esriFieldTypeSmallInteger","alias":"N/A","sqlType":"sqlTypeOther","nullable":true,"editable":true,"domain":null,"defaultValue":null},{"name":"Hospitalized","type":"esriFieldTypeInteger","alias":"Hospitalized","sqlType":"sqlTypeOther","nullable":true,"editable":true,"domain":null,"defaultValue":null},{"name":"Intubated","type":"esriFieldTypeInteger","alias":"Intubated","sqlType":"sqlTypeOther","nullable":true,"editable":true,"domain":null,"defaultValue":null},{"name":"Confirmed7day","type":"esriFieldTypeInteger","alias":"Confirmed7day","sqlType":"sqlTypeOther","nullable":true,"editable":true,"domain":null,"defaultValue":null},{"name":"Recovered7day","type":"esriFieldTypeInteger","alias":"Recovered7day","sqlType":"sqlTypeOther","nullable":true,"editable":true,"domain":null,"defaultValue":null},{"name":"Deaths7day","type":"esriFieldTypeInteger","alias":"Deaths7day","sqlType":"sqlTypeOther","nullable":true,"editable":true,"domain":null,"defaultValue":null},{"name":"Hopitalized7day","type":"esriFieldTypeInteger","alias":"Hopitalized7day","sqlType":"sqlTypeOther","nullable":true,"editable":true,"domain":null,"defaultValue":null},{"name":"reportedtPT","type":"esriFieldTypeString","alias":"reportedtPT","sqlType":"sqlTypeOther","length":20,"nullable":true,"editable":true,"domain":null,"defaultValue":null},{"name":"DateLess7","type":"esriFieldTypeString","alias":"DateLess7","sqlType":"sqlTypeOther","length":20,"nullable":true,"editable":true,"domain":null,"defaultValue":null},{"name":"Text1","type":"esriFieldTypeString","alias":"Text1","sqlType":"sqlTypeOther","length":20,"nullable":true,"editable":true,"domain":null,"defaultValue":null},{"name":"Text2","type":"esriFieldTypeString","alias":"Text2","sqlType":"sqlTypeOther","length":20,"nullable":true,"editable":true,"domain":null,"defaultValue":null},{"name":"Text3","type":"esriFieldTypeString","alias":"Text3","sqlType":"sqlTypeOther","length":20,"nullable":true,"editable":true,"domain":null,"defaultValue":null},{"name":"Text4","type":"esriFieldTypeString","alias":"Text4","sqlType":"sqlTypeOther","length":20,"nullable":true,"editable":true,"domain":null,"defaultValue":null},{"name":"Text5","type":"esriFieldTypeString","alias":"Text5","sqlType":"sqlTypeOther","length":20,"nullable":true,"editable":true,"domain":null,"defaultValue":null},{"name":"Int1","type":"esriFieldTypeInteger","alias":"Int1","sqlType":"sqlTypeOther","nullable":true,"editable":true,"domain":null,"defaultValue":null},{"name":"Int2","type":"esriFieldTypeInteger","alias":"Int2","sqlType":"sqlTypeOther","nullable":true,"editable":true,"domain":null,"defaultValue":null},{"name":"Int3","type":"esriFieldTypeInteger","alias":"Int3","sqlType":"sqlTypeOther","nullable":true,"editable":true,"domain":null,"defaultValue":null},{"name":"Int4","type":"esriFieldTypeInteger","alias":"Int4","sqlType":"sqlTypeOther","nullable":true,"editable":true,"domain":null,"defaultValue":null},{"name":"Int5","type":"esriFieldTypeInteger","alias":"Int5","sqlType":"sqlTypeOther","nullable":true,"editable":true,"domain":null,"defaultValue":null},{"name":"Dbl1","type":"esriFieldTypeDouble","alias":"Dbl1","sqlType":"sqlTypeOther","nullable":true,"editable":true,"domain":null,"defaultValue":null},{"name":"Dbl2","type":"esriFieldTypeDouble","alias":"Dbl2","sqlType":"sqlTypeOther","nullable":true,"editable":true,"domain":null,"defaultValue":null},{"name":"Dbl3","type":"esriFieldTypeDouble","alias":"Dbl3","sqlType":"sqlTypeOther","nullable":true,"editable":true,"domain":null,"defaultValue":null},{"name":"Dbl4","type":"esriFieldTypeDouble","alias":"Dbl4","sqlType":"sqlTypeOther","nullable":true,"editable":true,"domain":null,"defaultValue":null},{"name":"Dbl5","type":"esriFieldTypeDouble","alias":"Dbl5","sqlType":"sqlTypeOther","nullable":true,"editable":true,"domain":null,"defaultValue":null},{"name":"Date1","type":"esriFieldTypeDate","alias":"Date1","sqlType":"sqlTypeOther","length":0,"nullable":true,"editable":true,"domain":null,"defaultValue":null},{"name":"Date2","type":"esriFieldTypeDate","alias":"Date2","sqlType":"sqlTypeOther","length":0,"nullable":true,"editable":true,"domain":null,"defaultValue":null},{"name":"ObjectId","type":"esriFieldTypeOID","alias":"","sqlType":"sqlTypeOther","length":8,"nullable":false,"editable":false,"domain":null,"defaultValue":null}],"indexes":[{"name":"FDO_GlobalID","fields":"GlobalID","isAscending":true,"isUnique":true,"description":""},{"name":"G3name","fields":"name","isAscending":true,"isUnique":false,"description":""},{"name":"CreationDateIndex","fields":"CreationDate","isAscending":true,"isUnique":false,"description":"CreationDate Field index"},{"name":"CreatorIndex","fields":"Creator","isAscending":false,"isUnique":false,"description":"Creator Field index"},{"name":"EditDateIndex","fields":"EditDate","isAscending":true,"isUnique":false,"description":"EditDate Field index"},{"name":"EditorIndex","fields":"Editor","isAscending":false,"isUnique":false,"description":"Editor Field index"},{"name":"Shape__Area_Index","fields":"Shape__Area","isAscending":true,"isUnique":false,"description":""},{"name":"Shape__Length_Index","fields":"Shape__Length","isAscending":true,"isUnique":false,"description":""},{"name":"user_4176.Cases_REPORTING_AREAS_Shape_sidx","fields":"Shape","isAscending":false,"isUnique":false,"description":"Shape Index"}],"types":[],"templates":[{"name":"Boundaries","description":"","drawingTool":"esriFeatureEditToolPolygon","prototype":{"attributes":{"name":""}}}],"supportedQueryFormats":"JSON, geoJSON, PBF","hasStaticData":true,"maxRecordCount":2000,"standardMaxRecordCount":4000,"standardMaxRecordCountNoGeometry":32000,"tileMaxRecordCount":4000,"maxRecordCountFactor":1,"capabilities":"Query"}